<NewDataSet>
  <Table>
    <ID>0</ID>
    <Tipo>C</Tipo>
    <Codigo>0</Codigo>
    <NoPlu>0</NoPlu>
    <Descripcion>Carnes y Salchichonerias</Descripcion>
    <Precio>0</Precio>
    <Tipo1>0</Tipo1>
    <Ditable>0</Ditable>
    <Caducidad>0</Caducidad>
    <Impuesto>0</Impuesto>
    <Multiplo>0</Multiplo>
  </Table>
  <Table>
    <ID>1</ID>
    <Tipo>C</Tipo>
    <Codigo>0</Codigo>
    <NoPlu>0</NoPlu>
    <Descripcion>Carnes Frías</Descripcion>
    <Precio>0</Precio>
    <Tipo1>0</Tipo1>
    <Ditable>0</Ditable>
    <Caducidad>0</Caducidad>
    <Impuesto>0</Impuesto>
    <Multiplo>0</Multiplo>
    <Ingrediente>0</Ingrediente>
  </Table>
  <Table>
    <ID>3</ID>
    <Dependencia>1</Dependencia>
    <Tipo>C</Tipo>
    <Codigo>0</Codigo>
    <NoPlu>0</NoPlu>
    <Descripcion>Pastas Embutidas</Descripcion>
    <Precio>0</Precio>
    <Tipo1>0</Tipo1>
    <Ditable>0</Ditable>
    <Caducidad>0</Caducidad>
    <Impuesto>0</Impuesto>
    <Multiplo>0</Multiplo>
    <Ingrediente>0</Ingrediente>
  </Table>
  <Table>
    <ID>12</ID>
    <Dependencia>3</Dependencia>
    <Tipo>C</Tipo>
    <Codigo>0</Codigo>
    <NoPlu>0</NoPlu>
    <Descripcion>Mortadela</Descripcion>
    <Precio>0</Precio>
    <Tipo1>0</Tipo1>
    <Ditable>0</Ditable>
    <Caducidad>0</Caducidad>
    <Impuesto>0</Impuesto>
    <Multiplo>0</Multiplo>
    <Ingrediente>0</Ingrediente>
  </Table>
  <Table>
    <Tipo>P</Tipo>
    <Codigo>1</Codigo>
    <NoPlu>1</NoPlu>
    <Descripcion>OSCAR MAYER BOLOGNIA DE CERDO 227 GR PAQ</Descripcion>
    <Precio>23.9</Precio>
    <Tipo1>1</Tipo1>
    <Ditable>1</Ditable>
    <Caducidad>5</Caducidad>
    <Impuesto>0</Impuesto>
    <Multiplo>0</Multiplo>
    <Ingrediente>0</Ingrediente>
  </Table>
  <Table>
    <Tipo>P</Tipo>
    <Codigo>2</Codigo>
    <NoPlu>2</NoPlu>
    <Descripcion>CHIMEX MORTADELA </Descripcion>
    <Precio>23.9</Precio>
    <Tipo1>1</Tipo1>
    <Ditable>1</Ditable>
    <Caducidad>5</Caducidad>
    <Impuesto>0</Impuesto>
    <Multiplo>0</Multiplo>
    <Ingrediente>0</Ingrediente>
  </Table>
  <Table>
    <Tipo>P</Tipo>
    <Codigo>3</Codigo>
    <NoPlu>3</NoPlu>
    <Descripcion>FUD MORTADELA </Descripcion>
    <Precio>29.9</Precio>
    <Tipo1>1</Tipo1>
    <Ditable>1</Ditable>
    <Caducidad>5</Caducidad>
    <Impuesto>0</Impuesto>
    <Multiplo>0</Multiplo>
    <Ingrediente>0</Ingrediente>
  </Table>
  <Table>
    <Tipo>P</Tipo>
    <Codigo>4</Codigo>
    <NoPlu>4</NoPlu>
    <Descripcion>KIR MORTADELA </Descripcion>
    <Precio>23.9</Precio>
    <Tipo1>1</Tipo1>
    <Ditable>1</Ditable>
    <Caducidad>5</Caducidad>
    <Impuesto>0</Impuesto>
    <Multiplo>0</Multiplo>
    <Ingrediente>0</Ingrediente>
  </Table>
  <Table>
    <Tipo>P</Tipo>
    <Codigo>5</Codigo>
    <NoPlu>5</NoPlu>
    <Descripcion>BAFAR MORTADELA </Descripcion>
    <Precio>26.5</Precio>
    <Tipo1>1</Tipo1>
    <Ditable>1</Ditable>
    <Caducidad>5</Caducidad>
    <Impuesto>0</Impuesto>
    <Multiplo>0</Multiplo>
    <Ingrediente>0</Ingrediente>
  </Table>
  <Table>
    <Tipo>P</Tipo>
    <Codigo>6</Codigo>
    <NoPlu>6</NoPlu>
    <Descripcion>KIR MORTADELA 200 GRS 200 GR PAQ</Descripcion>
    <Precio>5.5</Precio>
    <Tipo1>1</Tipo1>
    <Ditable>1</Ditable>
    <Caducidad>5</Caducidad>
    <Impuesto>0</Impuesto>
    <Multiplo>0</Multiplo>
    <Ingrediente>0</Ingrediente>
  </Table>
  <Table>
    <Tipo>P</Tipo>
    <Codigo>7</Codigo>
    <NoPlu>7</NoPlu>
    <Descripcion>SUPREMO MORTADELA DE PAVO .</Descripcion>
    <Precio>29.9</Precio>
    <Tipo1>1</Tipo1>
    <Ditable>1</Ditable>
    <Caducidad>5</Caducidad>
    <Impuesto>0</Impuesto>
    <Multiplo>0</Multiplo>
    <Ingrediente>0</Ingrediente>
  </Table>
  <Table>
    <Tipo>P</Tipo>
    <Codigo>8</Codigo>
    <NoPlu>8</NoPlu>
    <Descripcion>SUPREMO MORTADELA DE PAVO .</Descripcion>
    <Precio>29.9</Precio>
    <Tipo1>1</Tipo1>
    <Ditable>1</Ditable>
    <Caducidad>5</Caducidad>
    <Impuesto>0</Impuesto>
    <Multiplo>0</Multiplo>
    <Ingrediente>0</Ingrediente>
  </Table>
  <Table>
    <Tipo>P</Tipo>
    <Codigo>9</Codigo>
    <NoPlu>9</NoPlu>
    <Descripcion>FRISCH BOLOGNIA PAPRIKA 190 GR PZ</Descripcion>
    <Precio>19.5</Precio>
    <Tipo1>1</Tipo1>
    <Ditable>1</Ditable>
    <Caducidad>5</Caducidad>
    <Impuesto>0</Impuesto>
    <Multiplo>0</Multiplo>
    <Ingrediente>0</Ingrediente>
  </Table>
  <Table>
    <Tipo>P</Tipo>
    <Codigo>10</Codigo>
    <NoPlu>10</NoPlu>
    <Descripcion>PONDEROSA MORTADELA DE CREDO 500 GR PAQ</Descripcion>
    <Precio>11.5</Precio>
    <Tipo1>1</Tipo1>
    <Ditable>1</Ditable>
    <Caducidad>5</Caducidad>
    <Impuesto>0</Impuesto>
    <Multiplo>0</Multiplo>
    <Ingrediente>0</Ingrediente>
  </Table>
  <Table>
    <ID>13</ID>
    <Dependencia>3</Dependencia>
    <Tipo>C</Tipo>
    <Codigo>0</Codigo>
    <NoPlu>0</NoPlu>
    <Descripcion>Pastel</Descripcion>
    <Precio>0</Precio>
    <Tipo1>0</Tipo1>
    <Ditable>0</Ditable>
    <Caducidad>0</Caducidad>
    <Impuesto>0</Impuesto>
    <Multiplo>0</Multiplo>
    <Ingrediente>0</Ingrediente>
  </Table>
  <Table>
    <Tipo>P</Tipo>
    <Codigo>11</Codigo>
    <NoPlu>11</NoPlu>
    <Descripcion>DUBY PASTEL PIMIENTO </Descripcion>
    <Precio>19.9</Precio>
    <Tipo1>1</Tipo1>
    <Ditable>0</Ditable>
    <Caducidad>6</Caducidad>
    <Impuesto>0</Impuesto>
    <Multiplo>0</Multiplo>
    <Ingrediente>0</Ingrediente>
  </Table>
  <Table>
    <Tipo>P</Tipo>
    <Codigo>12</Codigo>
    <NoPlu>12</NoPlu>
    <Descripcion>FUD PASTEL PIMIENTO </Descripcion>
    <Precio>39.9</Precio>
    <Tipo1>1</Tipo1>
    <Ditable>0</Ditable>
    <Caducidad>6</Caducidad>
    <Impuesto>0</Impuesto>
    <Multiplo>0</Multiplo>
    <Ingrediente>0</Ingrediente>
  </Table>
  <Table>
    <Tipo>P</Tipo>
    <Codigo>13</Codigo>
    <NoPlu>13</NoPlu>
    <Descripcion>BAFAR PASTEL C.CHILE JALAPENO </Descripcion>
    <Precio>31.5</Precio>
    <Tipo1>1</Tipo1>
    <Ditable>0</Ditable>
    <Caducidad>6</Caducidad>
    <Impuesto>0</Impuesto>
    <Multiplo>0</Multiplo>
    <Ingrediente>0</Ingrediente>
  </Table>
  <Table>
    <Tipo>P</Tipo>
    <Codigo>14</Codigo>
    <NoPlu>14</NoPlu>
    <Descripcion>CHIMEX PASTEL PIMIENTO </Descripcion>
    <Precio>31.9</Precio>
    <Tipo1>1</Tipo1>
    <Ditable>0</Ditable>
    <Caducidad>6</Caducidad>
    <Impuesto>0</Impuesto>
    <Multiplo>0</Multiplo>
    <Ingrediente>0</Ingrediente>
  </Table>
  <Table>
    <ID>14</ID>
    <Dependencia>3</Dependencia>
    <Tipo>C</Tipo>
    <Codigo>0</Codigo>
    <NoPlu>0</NoPlu>
    <Descripcion>Queso de puerco</Descripcion>
    <Precio>0</Precio>
    <Tipo1>0</Tipo1>
    <Ditable>0</Ditable>
    <Caducidad>0</Caducidad>
    <Impuesto>0</Impuesto>
    <Multiplo>0</Multiplo>
    <Ingrediente>0</Ingrediente>
  </Table>
  <Table>
    <Tipo>P</Tipo>
    <Codigo>15</Codigo>
    <NoPlu>15</NoPlu>
    <Descripcion>FUD QUESO DE PUERCO </Descripcion>
    <Precio>48.9</Precio>
    <Tipo1>1</Tipo1>
    <Ditable>0</Ditable>
    <Caducidad>7</Caducidad>
    <Impuesto>0</Impuesto>
    <Multiplo>0</Multiplo>
    <Ingrediente>0</Ingrediente>
  </Table>
  <Table>
    <Tipo>P</Tipo>
    <Codigo>16</Codigo>
    <NoPlu>16</NoPlu>
    <Descripcion>CAMPESTRE QUESO DE PUERCO </Descripcion>
    <Precio>55.5</Precio>
    <Tipo1>1</Tipo1>
    <Ditable>0</Ditable>
    <Caducidad>7</Caducidad>
    <Impuesto>0</Impuesto>
    <Multiplo>0</Multiplo>
    <Ingrediente>0</Ingrediente>
  </Table>
  <Table>
    <Tipo>P</Tipo>
    <Codigo>17</Codigo>
    <NoPlu>17</NoPlu>
    <Descripcion>DUBY QUESO PUERCO </Descripcion>
    <Precio>43.5</Precio>
    <Tipo1>1</Tipo1>
    <Ditable>0</Ditable>
    <Caducidad>7</Caducidad>
    <Impuesto>0</Impuesto>
    <Multiplo>0</Multiplo>
    <Ingrediente>0</Ingrediente>
  </Table>
  <Table>
    <Tipo>P</Tipo>
    <Codigo>18</Codigo>
    <NoPlu>18</NoPlu>
    <Descripcion>EL CERDITO QUESO DE PUERCO </Descripcion>
    <Precio>46.9</Precio>
    <Tipo1>1</Tipo1>
    <Ditable>0</Ditable>
    <Caducidad>7</Caducidad>
    <Impuesto>0</Impuesto>
    <Multiplo>0</Multiplo>
    <Ingrediente>0</Ingrediente>
  </Table>
  <Table>
    <Tipo>P</Tipo>
    <Codigo>19</Codigo>
    <NoPlu>19</NoPlu>
    <Descripcion>KUAL QUESO DE PUERCO </Descripcion>
    <Precio>41.5</Precio>
    <Tipo1>1</Tipo1>
    <Ditable>0</Ditable>
    <Caducidad>7</Caducidad>
    <Impuesto>0</Impuesto>
    <Multiplo>0</Multiplo>
    <Ingrediente>0</Ingrediente>
  </Table>
  <Table>
    <ID>15</ID>
    <Dependencia>3</Dependencia>
    <Tipo>C</Tipo>
    <Codigo>0</Codigo>
    <NoPlu>0</NoPlu>
    <Descripcion>Pathe</Descripcion>
    <Precio>0</Precio>
    <Tipo1>0</Tipo1>
    <Ditable>0</Ditable>
    <Caducidad>0</Caducidad>
    <Impuesto>0</Impuesto>
    <Multiplo>0</Multiplo>
    <Ingrediente>0</Ingrediente>
  </Table>
  <Table>
    <Tipo>P</Tipo>
    <Codigo>20</Codigo>
    <NoPlu>20</NoPlu>
    <Descripcion>ZWANCITO PATHE ENDIABLADO 100 GR PAQ</Descripcion>
    <Precio>9.1</Precio>
    <Tipo1>1</Tipo1>
    <Ditable>0</Ditable>
    <Caducidad>8</Caducidad>
    <Impuesto>0</Impuesto>
    <Multiplo>0</Multiplo>
    <Ingrediente>0</Ingrediente>
  </Table>
  <Table>
    <Tipo>P</Tipo>
    <Codigo>21</Codigo>
    <NoPlu>21</NoPlu>
    <Descripcion>ZWANCITO PATHE AHUMADO 100 GR PZ</Descripcion>
    <Precio>9.1</Precio>
    <Tipo1>1</Tipo1>
    <Ditable>0</Ditable>
    <Caducidad>8</Caducidad>
    <Impuesto>0</Impuesto>
    <Multiplo>0</Multiplo>
    <Ingrediente>0</Ingrediente>
  </Table>
  <Table>
    <Tipo>P</Tipo>
    <Codigo>22</Codigo>
    <NoPlu>22</NoPlu>
    <Descripcion>ZWAN PATHE DE HIGADO DE HIGADO DE HIGADO </Descripcion>
    <Precio>54.9</Precio>
    <Tipo1>1</Tipo1>
    <Ditable>0</Ditable>
    <Caducidad>8</Caducidad>
    <Impuesto>0</Impuesto>
    <Multiplo>0</Multiplo>
    <Ingrediente>0</Ingrediente>
  </Table>
  <Table>
    <Tipo>P</Tipo>
    <Codigo>23</Codigo>
    <NoPlu>23</NoPlu>
    <Descripcion>ZWANCITO PATHE SABOR CHIPOTLE 100 GR PZ</Descripcion>
    <Precio>9.1</Precio>
    <Tipo1>0</Tipo1>
    <Ditable>0</Ditable>
    <Caducidad>8</Caducidad>
    <Impuesto>0</Impuesto>
    <Multiplo>0</Multiplo>
    <Ingrediente>0</Ingrediente>
  </Table>
  <Table>
    <ID>4</ID>
    <Dependencia>1</Dependencia>
    <Tipo>C</Tipo>
    <Codigo>0</Codigo>
    <NoPlu>0</NoPlu>
    <Descripcion>Tocino ahumado</Descripcion>
    <Precio>0</Precio>
    <Tipo1>0</Tipo1>
    <Ditable>0</Ditable>
    <Caducidad>0</Caducidad>
    <Impuesto>0</Impuesto>
    <Multiplo>0</Multiplo>
    <Ingrediente>0</Ingrediente>
  </Table>
  <Table>
    <Tipo>P</Tipo>
    <Codigo>24</Codigo>
    <NoPlu>24</NoPlu>
    <Descripcion>FUD TOCINO AHUMADO DE CERDO 250 GR PAQ</Descripcion>
    <Precio>23.9</Precio>
    <Tipo1>0</Tipo1>
    <Ditable>0</Ditable>
    <Caducidad>9</Caducidad>
    <Impuesto>0</Impuesto>
    <Multiplo>0</Multiplo>
    <Ingrediente>0</Ingrediente>
  </Table>
  <Table>
    <Tipo>P</Tipo>
    <Codigo>25</Codigo>
    <NoPlu>25</NoPlu>
    <Descripcion>SAN RAFAEL TOCINO AHUMADO 340 GR PAQ</Descripcion>
    <Precio>37.5</Precio>
    <Tipo1>0</Tipo1>
    <Ditable>0</Ditable>
    <Caducidad>9</Caducidad>
    <Impuesto>0</Impuesto>
    <Multiplo>0</Multiplo>
    <Ingrediente>0</Ingrediente>
  </Table>
  <Table>
    <Tipo>P</Tipo>
    <Codigo>26</Codigo>
    <NoPlu>26</NoPlu>
    <Descripcion>SUPREMO TOCINO AHUMADO REBANADO .</Descripcion>
    <Precio>89.9</Precio>
    <Tipo1>1</Tipo1>
    <Ditable>1</Ditable>
    <Caducidad>9</Caducidad>
    <Impuesto>0</Impuesto>
    <Multiplo>0</Multiplo>
    <Ingrediente>0</Ingrediente>
  </Table>
  <Table>
    <Tipo>P</Tipo>
    <Codigo>27</Codigo>
    <NoPlu>27</NoPlu>
    <Descripcion>FUD TOCINO AHUMADO </Descripcion>
    <Precio>99.9</Precio>
    <Tipo1>1</Tipo1>
    <Ditable>1</Ditable>
    <Caducidad>9</Caducidad>
    <Impuesto>0</Impuesto>
    <Multiplo>0</Multiplo>
    <Ingrediente>0</Ingrediente>
  </Table>
  <Table>
    <Tipo>P</Tipo>
    <Codigo>28</Codigo>
    <NoPlu>28</NoPlu>
    <Descripcion>OSCAR MAYER TOCINO DE PAVO 340 GR PAQ</Descripcion>
    <Precio>41.5</Precio>
    <Tipo1>0</Tipo1>
    <Ditable>1</Ditable>
    <Caducidad>9</Caducidad>
    <Impuesto>0</Impuesto>
    <Multiplo>0</Multiplo>
    <Ingrediente>0</Ingrediente>
  </Table>
  <Table>
    <Tipo>P</Tipo>
    <Codigo>29</Codigo>
    <NoPlu>29</NoPlu>
    <Descripcion>PONDEROSA TOCINO AHUMADO </Descripcion>
    <Precio>79.9</Precio>
    <Tipo1>1</Tipo1>
    <Ditable>1</Ditable>
    <Caducidad>9</Caducidad>
    <Impuesto>0</Impuesto>
    <Multiplo>0</Multiplo>
    <Ingrediente>0</Ingrediente>
  </Table>
  <Table>
    <Tipo>P</Tipo>
    <Codigo>30</Codigo>
    <NoPlu>30</NoPlu>
    <Descripcion>EL CERDITO TOCINO AHUMADO </Descripcion>
    <Precio>99.9</Precio>
    <Tipo1>1</Tipo1>
    <Ditable>1</Ditable>
    <Caducidad>9</Caducidad>
    <Impuesto>0</Impuesto>
    <Multiplo>0</Multiplo>
    <Ingrediente>0</Ingrediente>
  </Table>
  <Table>
    <Tipo>P</Tipo>
    <Codigo>31</Codigo>
    <NoPlu>31</NoPlu>
    <Descripcion>OSCAR MAYER TOCINO AHUMADO DE CERDO 227 GR PAQ</Descripcion>
    <Precio>37.5</Precio>
    <Tipo1>0</Tipo1>
    <Ditable>1</Ditable>
    <Caducidad>9</Caducidad>
    <Impuesto>0</Impuesto>
    <Multiplo>0</Multiplo>
    <Ingrediente>0</Ingrediente>
  </Table>
  <Table>
    <Tipo>P</Tipo>
    <Codigo>32</Codigo>
    <NoPlu>32</NoPlu>
    <Descripcion>BAFAR TOCINO AHUMADO </Descripcion>
    <Precio>86.9</Precio>
    <Tipo1>1</Tipo1>
    <Ditable>1</Ditable>
    <Caducidad>9</Caducidad>
    <Impuesto>0</Impuesto>
    <Multiplo>0</Multiplo>
    <Ingrediente>0</Ingrediente>
  </Table>
  <Table>
    <Tipo>P</Tipo>
    <Codigo>33</Codigo>
    <NoPlu>33</NoPlu>
    <Descripcion>ZWAN TOCINO AHUMADO 340 GR PZ</Descripcion>
    <Precio>36.5</Precio>
    <Tipo1>0</Tipo1>
    <Ditable>1</Ditable>
    <Caducidad>9</Caducidad>
    <Impuesto>0</Impuesto>
    <Multiplo>0</Multiplo>
    <Ingrediente>0</Ingrediente>
  </Table>
  <Table>
    <Tipo>P</Tipo>
    <Codigo>34</Codigo>
    <NoPlu>34</NoPlu>
    <Descripcion>PONDEROSA TOCINO AHUMADO DE CERDO 200 GR PAQ</Descripcion>
    <Precio>18.5</Precio>
    <Tipo1>0</Tipo1>
    <Ditable>1</Ditable>
    <Caducidad>9</Caducidad>
    <Impuesto>0</Impuesto>
    <Multiplo>0</Multiplo>
    <Ingrediente>0</Ingrediente>
  </Table>
  <Table>
    <Tipo>P</Tipo>
    <Codigo>35</Codigo>
    <NoPlu>35</NoPlu>
    <Descripcion>SABORI TOCINO 340 GR PZ</Descripcion>
    <Precio>38.5</Precio>
    <Tipo1>0</Tipo1>
    <Ditable>1</Ditable>
    <Caducidad>9</Caducidad>
    <Impuesto>0</Impuesto>
    <Multiplo>0</Multiplo>
    <Ingrediente>0</Ingrediente>
  </Table>
  <Table>
    <Tipo>P</Tipo>
    <Codigo>36</Codigo>
    <NoPlu>36</NoPlu>
    <Descripcion>SUPREMO TOCINO AHUMADO 180 GR PAQ</Descripcion>
    <Precio>19.9</Precio>
    <Tipo1>0</Tipo1>
    <Ditable>1</Ditable>
    <Caducidad>9</Caducidad>
    <Impuesto>0</Impuesto>
    <Multiplo>0</Multiplo>
    <Ingrediente>0</Ingrediente>
  </Table>
  <Table>
    <Tipo>P</Tipo>
    <Codigo>37</Codigo>
    <NoPlu>37</NoPlu>
    <Descripcion>BAFAR TOCINO AHUMADO 250 GR PZ</Descripcion>
    <Precio>23.9</Precio>
    <Tipo1>0</Tipo1>
    <Ditable>1</Ditable>
    <Caducidad>9</Caducidad>
    <Impuesto>0</Impuesto>
    <Multiplo>0</Multiplo>
    <Ingrediente>0</Ingrediente>
  </Table>
  <Table>
    <Tipo>P</Tipo>
    <Codigo>38</Codigo>
    <NoPlu>38</NoPlu>
    <Descripcion>BURR TOCINO REBANADO 200 GR PAQ</Descripcion>
    <Precio>19.5</Precio>
    <Tipo1>0</Tipo1>
    <Ditable>1</Ditable>
    <Caducidad>9</Caducidad>
    <Impuesto>0</Impuesto>
    <Multiplo>0</Multiplo>
    <Ingrediente>0</Ingrediente>
  </Table>
  <Table>
    <Tipo>P</Tipo>
    <Codigo>39</Codigo>
    <NoPlu>39</NoPlu>
    <Descripcion>SABORI TOCINO 227 GR PZ</Descripcion>
    <Precio>26</Precio>
    <Tipo1>0</Tipo1>
    <Ditable>1</Ditable>
    <Caducidad>9</Caducidad>
    <Impuesto>0</Impuesto>
    <Multiplo>0</Multiplo>
    <Ingrediente>0</Ingrediente>
  </Table>
  <Table>
    <Tipo>P</Tipo>
    <Codigo>40</Codigo>
    <NoPlu>40</NoPlu>
    <Descripcion>KIR TOCINO 250 GR PZ</Descripcion>
    <Precio>26.5</Precio>
    <Tipo1>0</Tipo1>
    <Ditable>1</Ditable>
    <Caducidad>9</Caducidad>
    <Impuesto>0</Impuesto>
    <Multiplo>0</Multiplo>
    <Ingrediente>0</Ingrediente>
  </Table>
  <Table>
    <ID>5</ID>
    <Dependencia>1</Dependencia>
    <Tipo>C</Tipo>
    <Codigo>0</Codigo>
    <NoPlu>0</NoPlu>
    <Descripcion>Jamones</Descripcion>
    <Precio>0</Precio>
    <Tipo1>0</Tipo1>
    <Ditable>0</Ditable>
    <Caducidad>0</Caducidad>
    <Impuesto>0</Impuesto>
    <Multiplo>0</Multiplo>
    <Ingrediente>0</Ingrediente>
  </Table>
  <Table>
    <ID>16</ID>
    <Dependencia>5</Dependencia>
    <Tipo>C</Tipo>
    <Codigo>0</Codigo>
    <NoPlu>0</NoPlu>
    <Descripcion>Jamón americano</Descripcion>
    <Precio>0</Precio>
    <Tipo1>0</Tipo1>
    <Ditable>0</Ditable>
    <Caducidad>0</Caducidad>
    <Impuesto>0</Impuesto>
    <Multiplo>0</Multiplo>
    <Ingrediente>0</Ingrediente>
  </Table>
  <Table>
    <Tipo>P</Tipo>
    <Codigo>41</Codigo>
    <NoPlu>41</NoPlu>
    <Descripcion>KIR JAMÓN AMERICANO </Descripcion>
    <Precio>42.9</Precio>
    <Tipo1>1</Tipo1>
    <Ditable>0</Ditable>
    <Caducidad>10</Caducidad>
    <Impuesto>0</Impuesto>
    <Multiplo>0</Multiplo>
    <Ingrediente>0</Ingrediente>
  </Table>
  <Table>
    <Tipo>P</Tipo>
    <Codigo>42</Codigo>
    <NoPlu>42</NoPlu>
    <Descripcion>FUD JAMÓN AMERICANO DE PAVO </Descripcion>
    <Precio>53.5</Precio>
    <Tipo1>1</Tipo1>
    <Ditable>0</Ditable>
    <Caducidad>10</Caducidad>
    <Impuesto>0</Impuesto>
    <Multiplo>0</Multiplo>
    <Ingrediente>0</Ingrediente>
  </Table>
  <Table>
    <Tipo>P</Tipo>
    <Codigo>43</Codigo>
    <NoPlu>43</NoPlu>
    <Descripcion>CHIMEX JAMÓN AMERICANO </Descripcion>
    <Precio>39.9</Precio>
    <Tipo1>1</Tipo1>
    <Ditable>0</Ditable>
    <Caducidad>10</Caducidad>
    <Impuesto>0</Impuesto>
    <Multiplo>0</Multiplo>
    <Ingrediente>0</Ingrediente>
  </Table>
  <Table>
    <Tipo>P</Tipo>
    <Codigo>44</Codigo>
    <NoPlu>44</NoPlu>
    <Descripcion>FUD JAMÓN AMERICANO </Descripcion>
    <Precio>47.9</Precio>
    <Tipo1>1</Tipo1>
    <Ditable>0</Ditable>
    <Caducidad>10</Caducidad>
    <Impuesto>0</Impuesto>
    <Multiplo>0</Multiplo>
    <Ingrediente>0</Ingrediente>
  </Table>
  <Table>
    <Tipo>P</Tipo>
    <Codigo>45</Codigo>
    <NoPlu>45</NoPlu>
    <Descripcion>BAFAR JAMÓN AMERICANO </Descripcion>
    <Precio>38.9</Precio>
    <Tipo1>1</Tipo1>
    <Ditable>0</Ditable>
    <Caducidad>10</Caducidad>
    <Impuesto>0</Impuesto>
    <Multiplo>0</Multiplo>
    <Ingrediente>0</Ingrediente>
  </Table>
  <Table>
    <Tipo>P</Tipo>
    <Codigo>46</Codigo>
    <NoPlu>46</NoPlu>
    <Descripcion>PONDEROSA JAMÓN AMERICANO </Descripcion>
    <Precio>36.9</Precio>
    <Tipo1>1</Tipo1>
    <Ditable>0</Ditable>
    <Caducidad>10</Caducidad>
    <Impuesto>0</Impuesto>
    <Multiplo>0</Multiplo>
    <Ingrediente>0</Ingrediente>
  </Table>
  <Table>
    <Tipo>P</Tipo>
    <Codigo>47</Codigo>
    <NoPlu>47</NoPlu>
    <Descripcion>SUPREMO JAMÓN AMERICANO </Descripcion>
    <Precio>39.9</Precio>
    <Tipo1>1</Tipo1>
    <Ditable>0</Ditable>
    <Caducidad>10</Caducidad>
    <Impuesto>0</Impuesto>
    <Multiplo>0</Multiplo>
    <Ingrediente>0</Ingrediente>
  </Table>
  <Table>
    <ID>17</ID>
    <Dependencia>5</Dependencia>
    <Tipo>C</Tipo>
    <Codigo>0</Codigo>
    <NoPlu>0</NoPlu>
    <Descripcion>Jamón virginia</Descripcion>
    <Precio>0</Precio>
    <Tipo1>0</Tipo1>
    <Ditable>0</Ditable>
    <Caducidad>0</Caducidad>
    <Impuesto>0</Impuesto>
    <Multiplo>0</Multiplo>
    <Ingrediente>0</Ingrediente>
  </Table>
  <Table>
    <Tipo>P</Tipo>
    <Codigo>48</Codigo>
    <NoPlu>48</NoPlu>
    <Descripcion>FUD JAMÓN VIRGINIA DE PAVO </Descripcion>
    <Precio>61.5</Precio>
    <Tipo1>1</Tipo1>
    <Ditable>0</Ditable>
    <Caducidad>5</Caducidad>
    <Impuesto>0</Impuesto>
    <Multiplo>0</Multiplo>
    <Ingrediente>0</Ingrediente>
  </Table>
  <Table>
    <Tipo>P</Tipo>
    <Codigo>49</Codigo>
    <NoPlu>49</NoPlu>
    <Descripcion>ZWAN JAMÓN VIRGINIA </Descripcion>
    <Precio>56.9</Precio>
    <Tipo1>1</Tipo1>
    <Ditable>0</Ditable>
    <Caducidad>5</Caducidad>
    <Impuesto>0</Impuesto>
    <Multiplo>0</Multiplo>
    <Ingrediente>0</Ingrediente>
  </Table>
  <Table>
    <Tipo>P</Tipo>
    <Codigo>50</Codigo>
    <NoPlu>50</NoPlu>
    <Descripcion>FUD JAMÓN VIRGINIA </Descripcion>
    <Precio>59.9</Precio>
    <Tipo1>1</Tipo1>
    <Ditable>0</Ditable>
    <Caducidad>5</Caducidad>
    <Impuesto>0</Impuesto>
    <Multiplo>0</Multiplo>
    <Ingrediente>0</Ingrediente>
  </Table>
  <Table>
    <Tipo>P</Tipo>
    <Codigo>51</Codigo>
    <NoPlu>51</NoPlu>
    <Descripcion>BAFAR JAMÓN VIRGINIA DE PAVO </Descripcion>
    <Precio>55.5</Precio>
    <Tipo1>1</Tipo1>
    <Ditable>0</Ditable>
    <Caducidad>5</Caducidad>
    <Impuesto>0</Impuesto>
    <Multiplo>0</Multiplo>
    <Ingrediente>0</Ingrediente>
  </Table>
  <Table>
    <Tipo>P</Tipo>
    <Codigo>52</Codigo>
    <NoPlu>52</NoPlu>
    <Descripcion>KIR JAMÓN VIRGINIA DE PAVO </Descripcion>
    <Precio>49.9</Precio>
    <Tipo1>1</Tipo1>
    <Ditable>0</Ditable>
    <Caducidad>5</Caducidad>
    <Impuesto>0</Impuesto>
    <Multiplo>0</Multiplo>
    <Ingrediente>0</Ingrediente>
  </Table>
  <Table>
    <Tipo>P</Tipo>
    <Codigo>53</Codigo>
    <NoPlu>53</NoPlu>
    <Descripcion>CAMPESTRE JAMÓN VIRGINIA </Descripcion>
    <Precio>56.9</Precio>
    <Tipo1>1</Tipo1>
    <Ditable>0</Ditable>
    <Caducidad>5</Caducidad>
    <Impuesto>0</Impuesto>
    <Multiplo>0</Multiplo>
    <Ingrediente>0</Ingrediente>
  </Table>
  <Table>
    <Tipo>P</Tipo>
    <Codigo>54</Codigo>
    <NoPlu>54</NoPlu>
    <Descripcion>PONDEROSA JAMÓN VIRGINIA DE PAVO </Descripcion>
    <Precio>55.5</Precio>
    <Tipo1>1</Tipo1>
    <Ditable>0</Ditable>
    <Caducidad>5</Caducidad>
    <Impuesto>0</Impuesto>
    <Multiplo>0</Multiplo>
    <Ingrediente>0</Ingrediente>
  </Table>
  <Table>
    <Tipo>P</Tipo>
    <Codigo>55</Codigo>
    <NoPlu>55</NoPlu>
    <Descripcion>CARNELI JAMÓN PAVO T/VIRGINIA </Descripcion>
    <Precio>57.5</Precio>
    <Tipo1>1</Tipo1>
    <Ditable>0</Ditable>
    <Caducidad>5</Caducidad>
    <Impuesto>0</Impuesto>
    <Multiplo>0</Multiplo>
    <Ingrediente>0</Ingrediente>
  </Table>
  <Table>
    <ID>18</ID>
    <Dependencia>5</Dependencia>
    <Tipo>C</Tipo>
    <Codigo>0</Codigo>
    <NoPlu>0</NoPlu>
    <Descripcion>Jamón de pavo</Descripcion>
    <Precio>0</Precio>
    <Tipo1>0</Tipo1>
    <Ditable>0</Ditable>
    <Caducidad>0</Caducidad>
    <Impuesto>0</Impuesto>
    <Multiplo>0</Multiplo>
    <Ingrediente>0</Ingrediente>
  </Table>
  <Table>
    <Tipo>P</Tipo>
    <Codigo>56</Codigo>
    <NoPlu>56</NoPlu>
    <Descripcion>SAN RAFAEL PECHUGA DE PAVO </Descripcion>
    <Precio>93.5</Precio>
    <Tipo1>1</Tipo1>
    <Ditable>1</Ditable>
    <Caducidad>6</Caducidad>
    <Impuesto>0</Impuesto>
    <Multiplo>0</Multiplo>
    <Ingrediente>0</Ingrediente>
  </Table>
  <Table>
    <Tipo>P</Tipo>
    <Codigo>57</Codigo>
    <NoPlu>57</NoPlu>
    <Descripcion>SAN RAFAEL JAMÓN DE PAVO REAL </Descripcion>
    <Precio>93.9</Precio>
    <Tipo1>1</Tipo1>
    <Ditable>1</Ditable>
    <Caducidad>6</Caducidad>
    <Impuesto>0</Impuesto>
    <Multiplo>0</Multiplo>
    <Ingrediente>0</Ingrediente>
  </Table>
  <Table>
    <Tipo>P</Tipo>
    <Codigo>58</Codigo>
    <NoPlu>58</NoPlu>
    <Descripcion>CHIMEX JAMÓN DE PAVO </Descripcion>
    <Precio>45.5</Precio>
    <Tipo1>1</Tipo1>
    <Ditable>1</Ditable>
    <Caducidad>6</Caducidad>
    <Impuesto>0</Impuesto>
    <Multiplo>0</Multiplo>
    <Ingrediente>0</Ingrediente>
  </Table>
  <Table>
    <Tipo>P</Tipo>
    <Codigo>59</Codigo>
    <NoPlu>59</NoPlu>
    <Descripcion>SAN RAFAEL JAMÓN DE PAVO AHUMADO AHUMADO AHUMADO </Descripcion>
    <Precio>109.5</Precio>
    <Tipo1>1</Tipo1>
    <Ditable>1</Ditable>
    <Caducidad>6</Caducidad>
    <Impuesto>0</Impuesto>
    <Multiplo>0</Multiplo>
    <Ingrediente>0</Ingrediente>
  </Table>
  <Table>
    <Tipo>P</Tipo>
    <Codigo>60</Codigo>
    <NoPlu>60</NoPlu>
    <Descripcion>FUD PECHUGA DE PAVO </Descripcion>
    <Precio>99.9</Precio>
    <Tipo1>1</Tipo1>
    <Ditable>1</Ditable>
    <Caducidad>6</Caducidad>
    <Impuesto>0</Impuesto>
    <Multiplo>0</Multiplo>
    <Ingrediente>0</Ingrediente>
  </Table>
  <Table>
    <Tipo>P</Tipo>
    <Codigo>61</Codigo>
    <NoPlu>61</NoPlu>
    <Descripcion>FUD JAMÓN DE PAVO AHUMADO </Descripcion>
    <Precio>86.9</Precio>
    <Tipo1>1</Tipo1>
    <Ditable>1</Ditable>
    <Caducidad>6</Caducidad>
    <Impuesto>0</Impuesto>
    <Multiplo>0</Multiplo>
    <Ingrediente>0</Ingrediente>
  </Table>
  <Table>
    <Tipo>P</Tipo>
    <Codigo>62</Codigo>
    <NoPlu>62</NoPlu>
    <Descripcion>KIR JAMÓN DE PAVO AHUMADO AHUMADO AHUMADO .</Descripcion>
    <Precio>72.9</Precio>
    <Tipo1>1</Tipo1>
    <Ditable>1</Ditable>
    <Caducidad>6</Caducidad>
    <Impuesto>0</Impuesto>
    <Multiplo>0</Multiplo>
    <Ingrediente>0</Ingrediente>
  </Table>
  <Table>
    <Tipo>P</Tipo>
    <Codigo>63</Codigo>
    <NoPlu>63</NoPlu>
    <Descripcion>TANGAMANGA PECHUGA DE PAVO </Descripcion>
    <Precio>118.9</Precio>
    <Tipo1>1</Tipo1>
    <Ditable>1</Ditable>
    <Caducidad>6</Caducidad>
    <Impuesto>0</Impuesto>
    <Multiplo>0</Multiplo>
    <Ingrediente>0</Ingrediente>
  </Table>
  <Table>
    <Tipo>P</Tipo>
    <Codigo>64</Codigo>
    <NoPlu>64</NoPlu>
    <Descripcion>BAFAR JAMÓN DE PAVO </Descripcion>
    <Precio>42.5</Precio>
    <Tipo1>1</Tipo1>
    <Ditable>1</Ditable>
    <Caducidad>6</Caducidad>
    <Impuesto>0</Impuesto>
    <Multiplo>0</Multiplo>
    <Ingrediente>0</Ingrediente>
  </Table>
  <Table>
    <Tipo>P</Tipo>
    <Codigo>65</Codigo>
    <NoPlu>65</NoPlu>
    <Descripcion>PREMIUM TURK JAMÓN DE PAVO AHUMADO AHUMADO AHUMADO</Descripcion>
    <Precio>97.9</Precio>
    <Tipo1>1</Tipo1>
    <Ditable>1</Ditable>
    <Caducidad>6</Caducidad>
    <Impuesto>0</Impuesto>
    <Multiplo>0</Multiplo>
    <Ingrediente>0</Ingrediente>
  </Table>
  <Table>
    <Tipo>P</Tipo>
    <Codigo>66</Codigo>
    <NoPlu>66</NoPlu>
    <Descripcion>PONDEROSA JAMÓN PAVO </Descripcion>
    <Precio>39.9</Precio>
    <Tipo1>1</Tipo1>
    <Ditable>1</Ditable>
    <Caducidad>6</Caducidad>
    <Impuesto>0</Impuesto>
    <Multiplo>0</Multiplo>
    <Ingrediente>0</Ingrediente>
  </Table>
  <Table>
    <Tipo>P</Tipo>
    <Codigo>67</Codigo>
    <NoPlu>67</NoPlu>
    <Descripcion>TANGAMANGA JAMÓN DE PAVO </Descripcion>
    <Precio>110.5</Precio>
    <Tipo1>1</Tipo1>
    <Ditable>1</Ditable>
    <Caducidad>6</Caducidad>
    <Impuesto>0</Impuesto>
    <Multiplo>0</Multiplo>
    <Ingrediente>0</Ingrediente>
  </Table>
  <Table>
    <Tipo>P</Tipo>
    <Codigo>68</Codigo>
    <NoPlu>68</NoPlu>
    <Descripcion>BAFAR JAMÓN AHUMADO DE PAVO </Descripcion>
    <Precio>69.9</Precio>
    <Tipo1>1</Tipo1>
    <Ditable>1</Ditable>
    <Caducidad>6</Caducidad>
    <Impuesto>0</Impuesto>
    <Multiplo>0</Multiplo>
    <Ingrediente>0</Ingrediente>
  </Table>
  <Table>
    <Tipo>P</Tipo>
    <Codigo>69</Codigo>
    <NoPlu>69</NoPlu>
    <Descripcion>SUPREMO JAMÓN DE PAVO </Descripcion>
    <Precio>46.9</Precio>
    <Tipo1>1</Tipo1>
    <Ditable>1</Ditable>
    <Caducidad>6</Caducidad>
    <Impuesto>0</Impuesto>
    <Multiplo>0</Multiplo>
    <Ingrediente>0</Ingrediente>
  </Table>
  <Table>
    <Tipo>P</Tipo>
    <Codigo>70</Codigo>
    <NoPlu>70</NoPlu>
    <Descripcion>SABORI PECHUGA DE PAVO EXTRAFINA SABORI </Descripcion>
    <Precio>110.9</Precio>
    <Tipo1>1</Tipo1>
    <Ditable>1</Ditable>
    <Caducidad>6</Caducidad>
    <Impuesto>0</Impuesto>
    <Multiplo>0</Multiplo>
    <Ingrediente>0</Ingrediente>
  </Table>
  <Table>
    <Tipo>P</Tipo>
    <Codigo>71</Codigo>
    <NoPlu>71</NoPlu>
    <Descripcion>SABORI JAMÓN PAVO NATURAL </Descripcion>
    <Precio>92.9</Precio>
    <Tipo1>1</Tipo1>
    <Ditable>1</Ditable>
    <Caducidad>6</Caducidad>
    <Impuesto>0</Impuesto>
    <Multiplo>0</Multiplo>
    <Ingrediente>0</Ingrediente>
  </Table>
  <Table>
    <Tipo>P</Tipo>
    <Codigo>72</Codigo>
    <NoPlu>72</NoPlu>
    <Descripcion>BAFAR PECHUGA DE PAVO </Descripcion>
    <Precio>79.9</Precio>
    <Tipo1>1</Tipo1>
    <Ditable>1</Ditable>
    <Caducidad>6</Caducidad>
    <Impuesto>0</Impuesto>
    <Multiplo>0</Multiplo>
    <Ingrediente>0</Ingrediente>
  </Table>
  <Table>
    <Tipo>P</Tipo>
    <Codigo>73</Codigo>
    <NoPlu>73</NoPlu>
    <Descripcion>CARNELI PECHUGA PAVO </Descripcion>
    <Precio>91.5</Precio>
    <Tipo1>1</Tipo1>
    <Ditable>1</Ditable>
    <Caducidad>6</Caducidad>
    <Impuesto>0</Impuesto>
    <Multiplo>0</Multiplo>
    <Ingrediente>0</Ingrediente>
  </Table>
  <Table>
    <Tipo>P</Tipo>
    <Codigo>74</Codigo>
    <NoPlu>74</NoPlu>
    <Descripcion>CAROLINA TURKEY JAMÓN PICNIC D PAVO </Descripcion>
    <Precio>28.5</Precio>
    <Tipo1>1</Tipo1>
    <Ditable>1</Ditable>
    <Caducidad>6</Caducidad>
    <Impuesto>0</Impuesto>
    <Multiplo>0</Multiplo>
    <Ingrediente>0</Ingrediente>
  </Table>
  <Table>
    <Tipo>P</Tipo>
    <Codigo>75</Codigo>
    <NoPlu>75</NoPlu>
    <Descripcion>CAROLINA TURKEY PECHUGA DE PAVO AHUMADA PETITE </Descripcion>
    <Precio>84.9</Precio>
    <Tipo1>1</Tipo1>
    <Ditable>1</Ditable>
    <Caducidad>6</Caducidad>
    <Impuesto>0</Impuesto>
    <Multiplo>0</Multiplo>
    <Ingrediente>0</Ingrediente>
  </Table>
  <Table>
    <Tipo>P</Tipo>
    <Codigo>76</Codigo>
    <NoPlu>76</NoPlu>
    <Descripcion>CAROLINA TURKEY PECHUGA PREMIUM </Descripcion>
    <Precio>95.9</Precio>
    <Tipo1>1</Tipo1>
    <Ditable>1</Ditable>
    <Caducidad>6</Caducidad>
    <Impuesto>0</Impuesto>
    <Multiplo>0</Multiplo>
    <Ingrediente>0</Ingrediente>
  </Table>
  <Table>
    <Tipo>P</Tipo>
    <Codigo>77</Codigo>
    <NoPlu>77</NoPlu>
    <Descripcion>CAROLINA TURKEY PECHUGA TRADICIONAL </Descripcion>
    <Precio>97.5</Precio>
    <Tipo1>1</Tipo1>
    <Ditable>1</Ditable>
    <Caducidad>6</Caducidad>
    <Impuesto>0</Impuesto>
    <Multiplo>0</Multiplo>
    <Ingrediente>0</Ingrediente>
  </Table>
  <Table>
    <Tipo>P</Tipo>
    <Codigo>78</Codigo>
    <NoPlu>78</NoPlu>
    <Descripcion>SABORI JAMÓN PAVC/BIFIDUS </Descripcion>
    <Precio>104.9</Precio>
    <Tipo1>1</Tipo1>
    <Ditable>1</Ditable>
    <Caducidad>6</Caducidad>
    <Impuesto>0</Impuesto>
    <Multiplo>0</Multiplo>
    <Ingrediente>0</Ingrediente>
  </Table>
  <Table>
    <Tipo>P</Tipo>
    <Codigo>79</Codigo>
    <NoPlu>79</NoPlu>
    <Descripcion>SABORI PECHUGA FINAS HIERBAS </Descripcion>
    <Precio>135.5</Precio>
    <Tipo1>1</Tipo1>
    <Ditable>1</Ditable>
    <Caducidad>6</Caducidad>
    <Impuesto>0</Impuesto>
    <Multiplo>0</Multiplo>
    <Ingrediente>0</Ingrediente>
  </Table>
  <Table>
    <Tipo>P</Tipo>
    <Codigo>80</Codigo>
    <NoPlu>80</NoPlu>
    <Descripcion>SAN RAFAEL PECHUGA NATURAL </Descripcion>
    <Precio>106.5</Precio>
    <Tipo1>1</Tipo1>
    <Ditable>1</Ditable>
    <Caducidad>6</Caducidad>
    <Impuesto>0</Impuesto>
    <Multiplo>0</Multiplo>
    <Ingrediente>0</Ingrediente>
  </Table>
  <Table>
    <Tipo>P</Tipo>
    <Codigo>81</Codigo>
    <NoPlu>81</NoPlu>
    <Descripcion>SAN RAFAEL PECHUGA PAVO HORNEADO </Descripcion>
    <Precio>106.5</Precio>
    <Tipo1>1</Tipo1>
    <Ditable>1</Ditable>
    <Caducidad>6</Caducidad>
    <Impuesto>0</Impuesto>
    <Multiplo>0</Multiplo>
    <Ingrediente>0</Ingrediente>
  </Table>
  <Table>
    <Tipo>P</Tipo>
    <Codigo>82</Codigo>
    <NoPlu>82</NoPlu>
    <Descripcion>ZWAN JAMÓN PAVO NATURAL </Descripcion>
    <Precio>95.9</Precio>
    <Tipo1>1</Tipo1>
    <Ditable>1</Ditable>
    <Caducidad>6</Caducidad>
    <Impuesto>0</Impuesto>
    <Multiplo>0</Multiplo>
    <Ingrediente>0</Ingrediente>
  </Table>
  <Table>
    <Tipo>P</Tipo>
    <Codigo>83</Codigo>
    <NoPlu>83</NoPlu>
    <Descripcion>ZWAN PECHUGA DE PAVO </Descripcion>
    <Precio>99.9</Precio>
    <Tipo1>1</Tipo1>
    <Ditable>1</Ditable>
    <Caducidad>6</Caducidad>
    <Impuesto>0</Impuesto>
    <Multiplo>0</Multiplo>
    <Ingrediente>0</Ingrediente>
  </Table>
  <Table>
    <Tipo>P</Tipo>
    <Codigo>84</Codigo>
    <NoPlu>84</NoPlu>
    <Descripcion>ZWAN PECHUGA DE PAVO HORNEADA </Descripcion>
    <Precio>109.9</Precio>
    <Tipo1>1</Tipo1>
    <Ditable>1</Ditable>
    <Caducidad>6</Caducidad>
    <Impuesto>0</Impuesto>
    <Multiplo>0</Multiplo>
    <Ingrediente>0</Ingrediente>
  </Table>
  <Table>
    <ID>19</ID>
    <Dependencia>5</Dependencia>
    <Tipo>C</Tipo>
    <Codigo>0</Codigo>
    <NoPlu>0</NoPlu>
    <Descripcion>Jamón de pierna</Descripcion>
    <Precio>0</Precio>
    <Tipo1>0</Tipo1>
    <Ditable>0</Ditable>
    <Caducidad>0</Caducidad>
    <Impuesto>0</Impuesto>
    <Multiplo>0</Multiplo>
    <Ingrediente>0</Ingrediente>
  </Table>
  <Table>
    <Tipo>P</Tipo>
    <Codigo>85</Codigo>
    <NoPlu>85</NoPlu>
    <Descripcion>SAN RAFAEL JAMÓN DE PIERNA REAL </Descripcion>
    <Precio>99.9</Precio>
    <Tipo1>1</Tipo1>
    <Ditable>0</Ditable>
    <Caducidad>7</Caducidad>
    <Impuesto>0</Impuesto>
    <Multiplo>0</Multiplo>
    <Ingrediente>0</Ingrediente>
  </Table>
  <Table>
    <Tipo>P</Tipo>
    <Codigo>86</Codigo>
    <NoPlu>86</NoPlu>
    <Descripcion>FUD JAMÓN YORK </Descripcion>
    <Precio>109</Precio>
    <Tipo1>1</Tipo1>
    <Ditable>0</Ditable>
    <Caducidad>7</Caducidad>
    <Impuesto>0</Impuesto>
    <Multiplo>0</Multiplo>
    <Ingrediente>0</Ingrediente>
  </Table>
  <Table>
    <Tipo>P</Tipo>
    <Codigo>87</Codigo>
    <NoPlu>87</NoPlu>
    <Descripcion>ZWAN JAMÓN DE PIERNA </Descripcion>
    <Precio>99.9</Precio>
    <Tipo1>1</Tipo1>
    <Ditable>0</Ditable>
    <Caducidad>7</Caducidad>
    <Impuesto>0</Impuesto>
    <Multiplo>0</Multiplo>
    <Ingrediente>0</Ingrediente>
  </Table>
  <Table>
    <Tipo>P</Tipo>
    <Codigo>88</Codigo>
    <NoPlu>88</NoPlu>
    <Descripcion>FUD JAMÓN DE PIERNA SELECTO </Descripcion>
    <Precio>83.5</Precio>
    <Tipo1>1</Tipo1>
    <Ditable>0</Ditable>
    <Caducidad>7</Caducidad>
    <Impuesto>0</Impuesto>
    <Multiplo>0</Multiplo>
    <Ingrediente>0</Ingrediente>
  </Table>
  <Table>
    <Tipo>P</Tipo>
    <Codigo>89</Codigo>
    <NoPlu>89</NoPlu>
    <Descripcion>KIR JAMÓN DE PIERNA </Descripcion>
    <Precio>83.5</Precio>
    <Tipo1>1</Tipo1>
    <Ditable>0</Ditable>
    <Caducidad>7</Caducidad>
    <Impuesto>0</Impuesto>
    <Multiplo>0</Multiplo>
    <Ingrediente>0</Ingrediente>
  </Table>
  <Table>
    <Tipo>P</Tipo>
    <Codigo>90</Codigo>
    <NoPlu>90</NoPlu>
    <Descripcion>SABORI JAMÓN EXTRA FINO </Descripcion>
    <Precio>99.9</Precio>
    <Tipo1>1</Tipo1>
    <Ditable>0</Ditable>
    <Caducidad>7</Caducidad>
    <Impuesto>0</Impuesto>
    <Multiplo>0</Multiplo>
    <Ingrediente>0</Ingrediente>
  </Table>
  <Table>
    <Tipo>P</Tipo>
    <Codigo>91</Codigo>
    <NoPlu>91</NoPlu>
    <Descripcion>BAFAR JAMÓN YORK </Descripcion>
    <Precio>86.5</Precio>
    <Tipo1>1</Tipo1>
    <Ditable>0</Ditable>
    <Caducidad>7</Caducidad>
    <Impuesto>0</Impuesto>
    <Multiplo>0</Multiplo>
    <Ingrediente>0</Ingrediente>
  </Table>
  <Table>
    <Tipo>P</Tipo>
    <Codigo>92</Codigo>
    <NoPlu>92</NoPlu>
    <Descripcion>SAN RAFAEL JAMÓN PERNIL HORNEADO </Descripcion>
    <Precio>123.9</Precio>
    <Tipo1>1</Tipo1>
    <Ditable>0</Ditable>
    <Caducidad>7</Caducidad>
    <Impuesto>0</Impuesto>
    <Multiplo>0</Multiplo>
    <Ingrediente>0</Ingrediente>
  </Table>
  <Table>
    <Tipo>P</Tipo>
    <Codigo>93</Codigo>
    <NoPlu>93</NoPlu>
    <Descripcion>CAMPESTRE JAMÓN DE PIERNA </Descripcion>
    <Precio>96.5</Precio>
    <Tipo1>1</Tipo1>
    <Ditable>0</Ditable>
    <Caducidad>7</Caducidad>
    <Impuesto>0</Impuesto>
    <Multiplo>0</Multiplo>
    <Ingrediente>0</Ingrediente>
  </Table>
  <Table>
    <Tipo>P</Tipo>
    <Codigo>94</Codigo>
    <NoPlu>94</NoPlu>
    <Descripcion>SUPREMO JAMÓN TIPO YORK </Descripcion>
    <Precio>78.9</Precio>
    <Tipo1>1</Tipo1>
    <Ditable>0</Ditable>
    <Caducidad>7</Caducidad>
    <Impuesto>0</Impuesto>
    <Multiplo>0</Multiplo>
    <Ingrediente>0</Ingrediente>
  </Table>
  <Table>
    <Tipo>P</Tipo>
    <Codigo>95</Codigo>
    <NoPlu>95</NoPlu>
    <Descripcion>TANGAMANGA JAMÓN LISTON DORADO </Descripcion>
    <Precio>131.5</Precio>
    <Tipo1>1</Tipo1>
    <Ditable>0</Ditable>
    <Caducidad>7</Caducidad>
    <Impuesto>0</Impuesto>
    <Multiplo>0</Multiplo>
    <Ingrediente>0</Ingrediente>
  </Table>
  <Table>
    <Tipo>P</Tipo>
    <Codigo>96</Codigo>
    <NoPlu>96</NoPlu>
    <Descripcion>TANGAMANGA PIERNA SELVA NEGRA </Descripcion>
    <Precio>142.9</Precio>
    <Tipo1>1</Tipo1>
    <Ditable>0</Ditable>
    <Caducidad>7</Caducidad>
    <Impuesto>0</Impuesto>
    <Multiplo>0</Multiplo>
    <Ingrediente>0</Ingrediente>
  </Table>
  <Table>
    <Tipo>P</Tipo>
    <Codigo>97</Codigo>
    <NoPlu>97</NoPlu>
    <Descripcion>JAMÓN CON CARNES FRIAS </Descripcion>
    <Precio>26.5</Precio>
    <Tipo1>1</Tipo1>
    <Ditable>0</Ditable>
    <Caducidad>7</Caducidad>
    <Impuesto>0</Impuesto>
    <Multiplo>0</Multiplo>
    <Ingrediente>0</Ingrediente>
  </Table>
  <Table>
    <Tipo>P</Tipo>
    <Codigo>98</Codigo>
    <NoPlu>98</NoPlu>
    <Descripcion>JAMÓN CON CARNES FRIAS </Descripcion>
    <Precio>26.5</Precio>
    <Tipo1>1</Tipo1>
    <Ditable>0</Ditable>
    <Caducidad>7</Caducidad>
    <Impuesto>0</Impuesto>
    <Multiplo>0</Multiplo>
    <Ingrediente>0</Ingrediente>
  </Table>
  <Table>
    <Tipo>P</Tipo>
    <Codigo>99</Codigo>
    <NoPlu>99</NoPlu>
    <Descripcion>FUD JAMÓN DE PIERNA PREMIER </Descripcion>
    <Precio>57.9</Precio>
    <Tipo1>1</Tipo1>
    <Ditable>0</Ditable>
    <Caducidad>7</Caducidad>
    <Impuesto>0</Impuesto>
    <Multiplo>0</Multiplo>
    <Ingrediente>0</Ingrediente>
  </Table>
  <Table>
    <Tipo>P</Tipo>
    <Codigo>100</Codigo>
    <NoPlu>100</NoPlu>
    <Descripcion>PARMA JAMÓN AUT EUROPEO </Descripcion>
    <Precio>135.5</Precio>
    <Tipo1>1</Tipo1>
    <Ditable>0</Ditable>
    <Caducidad>7</Caducidad>
    <Impuesto>0</Impuesto>
    <Multiplo>0</Multiplo>
    <Ingrediente>0</Ingrediente>
  </Table>
  <Table>
    <Tipo>P</Tipo>
    <Codigo>101</Codigo>
    <NoPlu>101</NoPlu>
    <Descripcion>SABORI JAMÓN PIERNS/SALYC/OMEGA3Y6 </Descripcion>
    <Precio>104.9</Precio>
    <Tipo1>1</Tipo1>
    <Ditable>0</Ditable>
    <Caducidad>7</Caducidad>
    <Impuesto>0</Impuesto>
    <Multiplo>0</Multiplo>
    <Ingrediente>0</Ingrediente>
  </Table>
  <Table>
    <Tipo>P</Tipo>
    <Codigo>102</Codigo>
    <NoPlu>102</NoPlu>
    <Descripcion>SUPREMO JAMÓN DE PIERNA </Descripcion>
    <Precio>83.9</Precio>
    <Tipo1>1</Tipo1>
    <Ditable>0</Ditable>
    <Caducidad>7</Caducidad>
    <Impuesto>0</Impuesto>
    <Multiplo>0</Multiplo>
    <Ingrediente>0</Ingrediente>
  </Table>
  <Table>
    <ID>20</ID>
    <Dependencia>5</Dependencia>
    <Tipo>C</Tipo>
    <Codigo>0</Codigo>
    <NoPlu>0</NoPlu>
    <Descripcion>Jamón horneado</Descripcion>
    <Precio>0</Precio>
    <Tipo1>0</Tipo1>
    <Ditable>0</Ditable>
    <Caducidad>0</Caducidad>
    <Impuesto>0</Impuesto>
    <Multiplo>0</Multiplo>
    <Ingrediente>0</Ingrediente>
  </Table>
  <Table>
    <Tipo>P</Tipo>
    <Codigo>103</Codigo>
    <NoPlu>103</NoPlu>
    <Descripcion>CHIMEX JAMON HORNEADO </Descripcion>
    <Precio>44.5</Precio>
    <Tipo1>1</Tipo1>
    <Ditable>1</Ditable>
    <Caducidad>8</Caducidad>
    <Impuesto>0</Impuesto>
    <Multiplo>0</Multiplo>
    <Ingrediente>0</Ingrediente>
  </Table>
  <Table>
    <Tipo>P</Tipo>
    <Codigo>104</Codigo>
    <NoPlu>104</NoPlu>
    <Descripcion>FUD JAMON HORNEADO </Descripcion>
    <Precio>54.5</Precio>
    <Tipo1>1</Tipo1>
    <Ditable>1</Ditable>
    <Caducidad>8</Caducidad>
    <Impuesto>0</Impuesto>
    <Multiplo>0</Multiplo>
    <Ingrediente>0</Ingrediente>
  </Table>
  <Table>
    <Tipo>P</Tipo>
    <Codigo>105</Codigo>
    <NoPlu>105</NoPlu>
    <Descripcion>SUPREMO JAMON HORNEADO </Descripcion>
    <Precio>48.9</Precio>
    <Tipo1>1</Tipo1>
    <Ditable>1</Ditable>
    <Caducidad>8</Caducidad>
    <Impuesto>0</Impuesto>
    <Multiplo>0</Multiplo>
    <Ingrediente>0</Ingrediente>
  </Table>
  <Table>
    <Tipo>P</Tipo>
    <Codigo>106</Codigo>
    <NoPlu>106</NoPlu>
    <Descripcion>KIR JAMON HORNEADO </Descripcion>
    <Precio>53.5</Precio>
    <Tipo1>1</Tipo1>
    <Ditable>1</Ditable>
    <Caducidad>8</Caducidad>
    <Impuesto>0</Impuesto>
    <Multiplo>0</Multiplo>
    <Ingrediente>0</Ingrediente>
  </Table>
  <Table>
    <Tipo>P</Tipo>
    <Codigo>107</Codigo>
    <NoPlu>107</NoPlu>
    <Descripcion>PONDEROSA JAMON HORNEADO </Descripcion>
    <Precio>37.9</Precio>
    <Tipo1>1</Tipo1>
    <Ditable>1</Ditable>
    <Caducidad>8</Caducidad>
    <Impuesto>0</Impuesto>
    <Multiplo>0</Multiplo>
    <Ingrediente>0</Ingrediente>
  </Table>
  <Table>
    <Tipo>P</Tipo>
    <Codigo>108</Codigo>
    <NoPlu>108</NoPlu>
    <Descripcion>BAFAR JAMON HORNEADO CUADRADO </Descripcion>
    <Precio>45.5</Precio>
    <Tipo1>1</Tipo1>
    <Ditable>1</Ditable>
    <Caducidad>8</Caducidad>
    <Impuesto>0</Impuesto>
    <Multiplo>0</Multiplo>
    <Ingrediente>0</Ingrediente>
  </Table>
  <Table>
    <Tipo>P</Tipo>
    <Codigo>109</Codigo>
    <NoPlu>109</NoPlu>
    <Descripcion>DUBY JAMON NAPOLES </Descripcion>
    <Precio>41.9</Precio>
    <Tipo1>1</Tipo1>
    <Ditable>1</Ditable>
    <Caducidad>8</Caducidad>
    <Impuesto>0</Impuesto>
    <Multiplo>0</Multiplo>
    <Ingrediente>0</Ingrediente>
  </Table>
  <Table>
    <ID>6</ID>
    <Dependencia>1</Dependencia>
    <Tipo>C</Tipo>
    <Codigo>0</Codigo>
    <NoPlu>0</NoPlu>
    <Descripcion>Salchicha</Descripcion>
    <Precio>0</Precio>
    <Tipo1>0</Tipo1>
    <Ditable>0</Ditable>
    <Caducidad>0</Caducidad>
    <Impuesto>0</Impuesto>
    <Multiplo>0</Multiplo>
    <Ingrediente>0</Ingrediente>
  </Table>
  <Table>
    <ID>21</ID>
    <Dependencia>6</Dependencia>
    <Tipo>C</Tipo>
    <Codigo>0</Codigo>
    <NoPlu>0</NoPlu>
    <Descripcion>Frankfurt</Descripcion>
    <Precio>0</Precio>
    <Tipo1>0</Tipo1>
    <Ditable>0</Ditable>
    <Caducidad>0</Caducidad>
    <Impuesto>0</Impuesto>
    <Multiplo>0</Multiplo>
    <Ingrediente>0</Ingrediente>
  </Table>
  <Table>
    <Tipo>P</Tipo>
    <Codigo>110</Codigo>
    <NoPlu>110</NoPlu>
    <Descripcion>SAN RAFAEL SALCHICHA FRANKFURT </Descripcion>
    <Precio>47.9</Precio>
    <Tipo1>1</Tipo1>
    <Ditable>1</Ditable>
    <Caducidad>9</Caducidad>
    <Impuesto>0</Impuesto>
    <Multiplo>0</Multiplo>
    <Ingrediente>0</Ingrediente>
  </Table>
  <Table>
    <ID>22</ID>
    <Dependencia>6</Dependencia>
    <Tipo>C</Tipo>
    <Codigo>0</Codigo>
    <NoPlu>0</NoPlu>
    <Descripcion>De pavo frankfurt</Descripcion>
    <Precio>0</Precio>
    <Tipo1>0</Tipo1>
    <Ditable>0</Ditable>
    <Caducidad>0</Caducidad>
    <Impuesto>0</Impuesto>
    <Multiplo>0</Multiplo>
    <Ingrediente>0</Ingrediente>
  </Table>
  <Table>
    <Tipo>P</Tipo>
    <Codigo>111</Codigo>
    <NoPlu>111</NoPlu>
    <Descripcion>BAFAR SALCHICHA FRANKFURT PAVO </Descripcion>
    <Precio>27.9</Precio>
    <Tipo1>1</Tipo1>
    <Ditable>1</Ditable>
    <Caducidad>10</Caducidad>
    <Impuesto>0</Impuesto>
    <Multiplo>0</Multiplo>
    <Ingrediente>0</Ingrediente>
  </Table>
  <Table>
    <ID>23</ID>
    <Dependencia>6</Dependencia>
    <Tipo>C</Tipo>
    <Codigo>0</Codigo>
    <NoPlu>0</NoPlu>
    <Descripcion>De pavo viena</Descripcion>
    <Precio>0</Precio>
    <Tipo1>0</Tipo1>
    <Ditable>0</Ditable>
    <Caducidad>0</Caducidad>
    <Impuesto>0</Impuesto>
    <Multiplo>0</Multiplo>
    <Ingrediente>0</Ingrediente>
  </Table>
  <Table>
    <Tipo>P</Tipo>
    <Codigo>112</Codigo>
    <NoPlu>112</NoPlu>
    <Descripcion>SAN RAFAEL SALCHICHA DE PAVO </Descripcion>
    <Precio>44.5</Precio>
    <Tipo1>1</Tipo1>
    <Ditable>1</Ditable>
    <Caducidad>5</Caducidad>
    <Impuesto>0</Impuesto>
    <Multiplo>0</Multiplo>
    <Ingrediente>0</Ingrediente>
  </Table>
  <Table>
    <Tipo>P</Tipo>
    <Codigo>113</Codigo>
    <NoPlu>113</NoPlu>
    <Descripcion>FUD SALCHICHA DE PAVO </Descripcion>
    <Precio>36.5</Precio>
    <Tipo1>1</Tipo1>
    <Ditable>1</Ditable>
    <Caducidad>5</Caducidad>
    <Impuesto>0</Impuesto>
    <Multiplo>0</Multiplo>
    <Ingrediente>0</Ingrediente>
  </Table>
  <Table>
    <Tipo>P</Tipo>
    <Codigo>114</Codigo>
    <NoPlu>114</NoPlu>
    <Descripcion>KIR SALCHICHA DE PAVO DE PAVO DE PAVO </Descripcion>
    <Precio>32.9</Precio>
    <Tipo1>1</Tipo1>
    <Ditable>1</Ditable>
    <Caducidad>5</Caducidad>
    <Impuesto>0</Impuesto>
    <Multiplo>0</Multiplo>
    <Ingrediente>0</Ingrediente>
  </Table>
  <Table>
    <Tipo>P</Tipo>
    <Codigo>115</Codigo>
    <NoPlu>115</NoPlu>
    <Descripcion>CHIMEX SALCHICHA DE PAVO </Descripcion>
    <Precio>31.5</Precio>
    <Tipo1>1</Tipo1>
    <Ditable>1</Ditable>
    <Caducidad>5</Caducidad>
    <Impuesto>0</Impuesto>
    <Multiplo>0</Multiplo>
    <Ingrediente>0</Ingrediente>
  </Table>
  <Table>
    <Tipo>P</Tipo>
    <Codigo>116</Codigo>
    <NoPlu>116</NoPlu>
    <Descripcion>FUD SALCHICHA JUMBO DE PAVO </Descripcion>
    <Precio>37.9</Precio>
    <Tipo1>1</Tipo1>
    <Ditable>1</Ditable>
    <Caducidad>5</Caducidad>
    <Impuesto>0</Impuesto>
    <Multiplo>0</Multiplo>
    <Ingrediente>0</Ingrediente>
  </Table>
  <Table>
    <Tipo>P</Tipo>
    <Codigo>117</Codigo>
    <NoPlu>117</NoPlu>
    <Descripcion>PREMIUM TURK SALCHICHA DE PAVO </Descripcion>
    <Precio>37.5</Precio>
    <Tipo1>1</Tipo1>
    <Ditable>1</Ditable>
    <Caducidad>5</Caducidad>
    <Impuesto>0</Impuesto>
    <Multiplo>0</Multiplo>
    <Ingrediente>0</Ingrediente>
  </Table>
  <Table>
    <Tipo>P</Tipo>
    <Codigo>118</Codigo>
    <NoPlu>118</NoPlu>
    <Descripcion>PONDEROSA SALCHICHA PAVO </Descripcion>
    <Precio>27.5</Precio>
    <Tipo1>1</Tipo1>
    <Ditable>1</Ditable>
    <Caducidad>5</Caducidad>
    <Impuesto>0</Impuesto>
    <Multiplo>0</Multiplo>
    <Ingrediente>0</Ingrediente>
  </Table>
  <Table>
    <Tipo>P</Tipo>
    <Codigo>119</Codigo>
    <NoPlu>119</NoPlu>
    <Descripcion>SUPREMO SALCHICHA DE PAVO </Descripcion>
    <Precio>32.9</Precio>
    <Tipo1>1</Tipo1>
    <Ditable>1</Ditable>
    <Caducidad>5</Caducidad>
    <Impuesto>0</Impuesto>
    <Multiplo>0</Multiplo>
    <Ingrediente>0</Ingrediente>
  </Table>
  <Table>
    <Tipo>P</Tipo>
    <Codigo>120</Codigo>
    <NoPlu>120</NoPlu>
    <Descripcion>SABORI SALCHICHA DE PAVO </Descripcion>
    <Precio>42.9</Precio>
    <Tipo1>1</Tipo1>
    <Ditable>1</Ditable>
    <Caducidad>5</Caducidad>
    <Impuesto>0</Impuesto>
    <Multiplo>0</Multiplo>
    <Ingrediente>0</Ingrediente>
  </Table>
  <Table>
    <Tipo>P</Tipo>
    <Codigo>121</Codigo>
    <NoPlu>121</NoPlu>
    <Descripcion>CARNELI SALCHICHA PAVO </Descripcion>
    <Precio>36.9</Precio>
    <Tipo1>1</Tipo1>
    <Ditable>1</Ditable>
    <Caducidad>5</Caducidad>
    <Impuesto>0</Impuesto>
    <Multiplo>0</Multiplo>
    <Ingrediente>0</Ingrediente>
  </Table>
  <Table>
    <ID>24</ID>
    <Dependencia>6</Dependencia>
    <Tipo>C</Tipo>
    <Codigo>0</Codigo>
    <NoPlu>0</NoPlu>
    <Descripcion>Viena / hot-dog</Descripcion>
    <Precio>0</Precio>
    <Tipo1>0</Tipo1>
    <Ditable>0</Ditable>
    <Caducidad>0</Caducidad>
    <Impuesto>0</Impuesto>
    <Multiplo>0</Multiplo>
    <Ingrediente>0</Ingrediente>
  </Table>
  <Table>
    <Tipo>P</Tipo>
    <Codigo>122</Codigo>
    <NoPlu>122</NoPlu>
    <Descripcion>KIR SALCHICHA VIENA </Descripcion>
    <Precio>26.5</Precio>
    <Tipo1>1</Tipo1>
    <Ditable>1</Ditable>
    <Caducidad>6</Caducidad>
    <Impuesto>0</Impuesto>
    <Multiplo>0</Multiplo>
    <Ingrediente>0</Ingrediente>
  </Table>
  <Table>
    <Tipo>P</Tipo>
    <Codigo>123</Codigo>
    <NoPlu>123</NoPlu>
    <Descripcion>FUD SALCHICHA HOT DOG </Descripcion>
    <Precio>27.5</Precio>
    <Tipo1>1</Tipo1>
    <Ditable>1</Ditable>
    <Caducidad>6</Caducidad>
    <Impuesto>0</Impuesto>
    <Multiplo>0</Multiplo>
    <Ingrediente>0</Ingrediente>
  </Table>
  <Table>
    <Tipo>P</Tipo>
    <Codigo>124</Codigo>
    <NoPlu>124</NoPlu>
    <Descripcion>SAN RAFAEL SALCHICHA VIENA </Descripcion>
    <Precio>34.9</Precio>
    <Tipo1>1</Tipo1>
    <Ditable>1</Ditable>
    <Caducidad>6</Caducidad>
    <Impuesto>0</Impuesto>
    <Multiplo>0</Multiplo>
    <Ingrediente>0</Ingrediente>
  </Table>
  <Table>
    <Tipo>P</Tipo>
    <Codigo>125</Codigo>
    <NoPlu>125</NoPlu>
    <Descripcion>DUBY SALCHICHA VIENA </Descripcion>
    <Precio>19.5</Precio>
    <Tipo1>1</Tipo1>
    <Ditable>1</Ditable>
    <Caducidad>6</Caducidad>
    <Impuesto>0</Impuesto>
    <Multiplo>0</Multiplo>
    <Ingrediente>0</Ingrediente>
  </Table>
  <Table>
    <Tipo>P</Tipo>
    <Codigo>126</Codigo>
    <NoPlu>126</NoPlu>
    <Descripcion>ZWAN SALCHICHA VIENESA </Descripcion>
    <Precio>31.9</Precio>
    <Tipo1>1</Tipo1>
    <Ditable>1</Ditable>
    <Caducidad>6</Caducidad>
    <Impuesto>0</Impuesto>
    <Multiplo>0</Multiplo>
    <Ingrediente>0</Ingrediente>
  </Table>
  <Table>
    <Tipo>P</Tipo>
    <Codigo>127</Codigo>
    <NoPlu>127</NoPlu>
    <Descripcion>KIR SALCHICHA HOT DOG </Descripcion>
    <Precio>25.62</Precio>
    <Tipo1>1</Tipo1>
    <Ditable>1</Ditable>
    <Caducidad>6</Caducidad>
    <Impuesto>0</Impuesto>
    <Multiplo>0</Multiplo>
    <Ingrediente>0</Ingrediente>
  </Table>
  <Table>
    <Tipo>P</Tipo>
    <Codigo>128</Codigo>
    <NoPlu>128</NoPlu>
    <Descripcion>CHIMEX SALCHICHA HOT DOG </Descripcion>
    <Precio>24.5</Precio>
    <Tipo1>1</Tipo1>
    <Ditable>1</Ditable>
    <Caducidad>6</Caducidad>
    <Impuesto>0</Impuesto>
    <Multiplo>0</Multiplo>
    <Ingrediente>0</Ingrediente>
  </Table>
  <Table>
    <Tipo>P</Tipo>
    <Codigo>129</Codigo>
    <NoPlu>129</NoPlu>
    <Descripcion>CHIMEX SALCHICHA VIENA DIARIA .</Descripcion>
    <Precio>21.9</Precio>
    <Tipo1>1</Tipo1>
    <Ditable>1</Ditable>
    <Caducidad>6</Caducidad>
    <Impuesto>0</Impuesto>
    <Multiplo>0</Multiplo>
    <Ingrediente>0</Ingrediente>
  </Table>
  <Table>
    <Tipo>P</Tipo>
    <Codigo>130</Codigo>
    <NoPlu>130</NoPlu>
    <Descripcion>BAFAR SALCHICHA VIENA </Descripcion>
    <Precio>27.5</Precio>
    <Tipo1>1</Tipo1>
    <Ditable>1</Ditable>
    <Caducidad>6</Caducidad>
    <Impuesto>0</Impuesto>
    <Multiplo>0</Multiplo>
    <Ingrediente>0</Ingrediente>
  </Table>
  <Table>
    <Tipo>P</Tipo>
    <Codigo>131</Codigo>
    <NoPlu>131</NoPlu>
    <Descripcion>FUD SALCHICHA JUMBO </Descripcion>
    <Precio>29.9</Precio>
    <Tipo1>1</Tipo1>
    <Ditable>1</Ditable>
    <Caducidad>6</Caducidad>
    <Impuesto>0</Impuesto>
    <Multiplo>0</Multiplo>
    <Ingrediente>0</Ingrediente>
  </Table>
  <Table>
    <Tipo>P</Tipo>
    <Codigo>132</Codigo>
    <NoPlu>132</NoPlu>
    <Descripcion>PONDEROSA SALCHICHA VIENA HEMBURGO </Descripcion>
    <Precio>19.9</Precio>
    <Tipo1>1</Tipo1>
    <Ditable>1</Ditable>
    <Caducidad>6</Caducidad>
    <Impuesto>0</Impuesto>
    <Multiplo>0</Multiplo>
    <Ingrediente>0</Ingrediente>
  </Table>
  <Table>
    <Tipo>P</Tipo>
    <Codigo>133</Codigo>
    <NoPlu>133</NoPlu>
    <Descripcion>EL CERDITO SALCHICHA HOT DOG </Descripcion>
    <Precio>31.5</Precio>
    <Tipo1>1</Tipo1>
    <Ditable>1</Ditable>
    <Caducidad>6</Caducidad>
    <Impuesto>0</Impuesto>
    <Multiplo>0</Multiplo>
    <Ingrediente>0</Ingrediente>
  </Table>
  <Table>
    <ID>25</ID>
    <Dependencia>6</Dependencia>
    <Tipo>C</Tipo>
    <Codigo>0</Codigo>
    <NoPlu>0</NoPlu>
    <Descripcion>Cocktail</Descripcion>
    <Precio>0</Precio>
    <Tipo1>0</Tipo1>
    <Ditable>0</Ditable>
    <Caducidad>0</Caducidad>
    <Impuesto>0</Impuesto>
    <Multiplo>0</Multiplo>
    <Ingrediente>0</Ingrediente>
  </Table>
  <Table>
    <Tipo>P</Tipo>
    <Codigo>134</Codigo>
    <NoPlu>134</NoPlu>
    <Descripcion>ZWAN SALCHICHA COCTELERA </Descripcion>
    <Precio>38.9</Precio>
    <Tipo1>1</Tipo1>
    <Ditable>1</Ditable>
    <Caducidad>7</Caducidad>
    <Impuesto>0</Impuesto>
    <Multiplo>0</Multiplo>
    <Ingrediente>0</Ingrediente>
  </Table>
  <Table>
    <Tipo>P</Tipo>
    <Codigo>135</Codigo>
    <NoPlu>135</NoPlu>
    <Descripcion>PREMIUM TURKEY SALCHICHA COCKTEL .</Descripcion>
    <Precio>47.9</Precio>
    <Tipo1>1</Tipo1>
    <Ditable>1</Ditable>
    <Caducidad>7</Caducidad>
    <Impuesto>0</Impuesto>
    <Multiplo>0</Multiplo>
    <Ingrediente>0</Ingrediente>
  </Table>
  <Table>
    <ID>26</ID>
    <Dependencia>6</Dependencia>
    <Tipo>C</Tipo>
    <Codigo>0</Codigo>
    <NoPlu>0</NoPlu>
    <Descripcion>Salchicha p/asar</Descripcion>
    <Precio>0</Precio>
    <Tipo1>0</Tipo1>
    <Ditable>0</Ditable>
    <Caducidad>0</Caducidad>
    <Impuesto>0</Impuesto>
    <Multiplo>0</Multiplo>
    <Ingrediente>0</Ingrediente>
  </Table>
  <Table>
    <Tipo>P</Tipo>
    <Codigo>136</Codigo>
    <NoPlu>136</NoPlu>
    <Descripcion>SORIANA SALCHICHA P/ASAR 800 GR PAQ</Descripcion>
    <Precio>24.5</Precio>
    <Tipo1>0</Tipo1>
    <Ditable>0</Ditable>
    <Caducidad>8</Caducidad>
    <Impuesto>0</Impuesto>
    <Multiplo>0</Multiplo>
    <Ingrediente>0</Ingrediente>
  </Table>
  <Table>
    <Tipo>P</Tipo>
    <Codigo>137</Codigo>
    <NoPlu>137</NoPlu>
    <Descripcion>KIR SALCHICHA P/ASAR 800 GR PAQ</Descripcion>
    <Precio>32.9</Precio>
    <Tipo1>0</Tipo1>
    <Ditable>0</Ditable>
    <Caducidad>8</Caducidad>
    <Impuesto>0</Impuesto>
    <Multiplo>0</Multiplo>
    <Ingrediente>0</Ingrediente>
  </Table>
  <Table>
    <Tipo>P</Tipo>
    <Codigo>138</Codigo>
    <NoPlu>138</NoPlu>
    <Descripcion>PONDEROSA SALCHICHA P/ASAR 8 PZ PAQ</Descripcion>
    <Precio>26.9</Precio>
    <Tipo1>0</Tipo1>
    <Ditable>0</Ditable>
    <Caducidad>8</Caducidad>
    <Impuesto>0</Impuesto>
    <Multiplo>0</Multiplo>
    <Ingrediente>0</Ingrediente>
  </Table>
  <Table>
    <Tipo>P</Tipo>
    <Codigo>139</Codigo>
    <NoPlu>139</NoPlu>
    <Descripcion>CHIMEX SALCHICHA P/ASAR 800 GR PZ</Descripcion>
    <Precio>31.5</Precio>
    <Tipo1>0</Tipo1>
    <Ditable>0</Ditable>
    <Caducidad>8</Caducidad>
    <Impuesto>0</Impuesto>
    <Multiplo>0</Multiplo>
    <Ingrediente>0</Ingrediente>
  </Table>
  <Table>
    <Tipo>P</Tipo>
    <Codigo>140</Codigo>
    <NoPlu>140</NoPlu>
    <Descripcion>KIR SALCHICHA P/ASAR C/TOCINO C/TOCINO C/TOCINO 800 GR PAQ</Descripcion>
    <Precio>35.5</Precio>
    <Tipo1>0</Tipo1>
    <Ditable>0</Ditable>
    <Caducidad>8</Caducidad>
    <Impuesto>0</Impuesto>
    <Multiplo>0</Multiplo>
    <Ingrediente>0</Ingrediente>
  </Table>
  <Table>
    <Tipo>P</Tipo>
    <Codigo>141</Codigo>
    <NoPlu>141</NoPlu>
    <Descripcion>CAMPESTRE SALCHICHA P/ASAR 800 GR PZ</Descripcion>
    <Precio>31.5</Precio>
    <Tipo1>0</Tipo1>
    <Ditable>0</Ditable>
    <Caducidad>8</Caducidad>
    <Impuesto>0</Impuesto>
    <Multiplo>0</Multiplo>
    <Ingrediente>0</Ingrediente>
  </Table>
  <Table>
    <Tipo>P</Tipo>
    <Codigo>142</Codigo>
    <NoPlu>142</NoPlu>
    <Descripcion>PONDEROSA SALCHICHA P/ASAR POLAKA 450 GR PAQ</Descripcion>
    <Precio>25.5</Precio>
    <Tipo1>0</Tipo1>
    <Ditable>0</Ditable>
    <Caducidad>8</Caducidad>
    <Impuesto>0</Impuesto>
    <Multiplo>0</Multiplo>
    <Ingrediente>0</Ingrediente>
  </Table>
  <Table>
    <Tipo>P</Tipo>
    <Codigo>143</Codigo>
    <NoPlu>143</NoPlu>
    <Descripcion>SORIANA SALCHICHA P/ASAR POLAKA POLAKA POLAKA 450 GR PAQ</Descripcion>
    <Precio>23.9</Precio>
    <Tipo1>0</Tipo1>
    <Ditable>0</Ditable>
    <Caducidad>8</Caducidad>
    <Impuesto>0</Impuesto>
    <Multiplo>0</Multiplo>
    <Ingrediente>0</Ingrediente>
  </Table>
  <Table>
    <Tipo>P</Tipo>
    <Codigo>144</Codigo>
    <NoPlu>144</NoPlu>
    <Descripcion>PONDEROSA SALCHICHA P/ASAR 400 GR PAQ</Descripcion>
    <Precio>14.5</Precio>
    <Tipo1>0</Tipo1>
    <Ditable>0</Ditable>
    <Caducidad>8</Caducidad>
    <Impuesto>0</Impuesto>
    <Multiplo>0</Multiplo>
    <Ingrediente>0</Ingrediente>
  </Table>
  <Table>
    <Tipo>P</Tipo>
    <Codigo>145</Codigo>
    <NoPlu>145</NoPlu>
    <Descripcion>BAFAR SALCHICHA P/ASAR CON QUESO 800 GR PAQ</Descripcion>
    <Precio>24.5</Precio>
    <Tipo1>0</Tipo1>
    <Ditable>0</Ditable>
    <Caducidad>8</Caducidad>
    <Impuesto>0</Impuesto>
    <Multiplo>0</Multiplo>
    <Ingrediente>0</Ingrediente>
  </Table>
  <Table>
    <Tipo>P</Tipo>
    <Codigo>146</Codigo>
    <NoPlu>146</NoPlu>
    <Descripcion>BAFAR SALCHICHA PARA ASAR DE PAVO 800 GR PZ</Descripcion>
    <Precio>26.5</Precio>
    <Tipo1>0</Tipo1>
    <Ditable>0</Ditable>
    <Caducidad>8</Caducidad>
    <Impuesto>0</Impuesto>
    <Multiplo>0</Multiplo>
    <Ingrediente>0</Ingrediente>
  </Table>
  <Table>
    <Tipo>P</Tipo>
    <Codigo>147</Codigo>
    <NoPlu>147</NoPlu>
    <Descripcion>FRISCH SALCHICHA P/ASAR 600 GR PZ</Descripcion>
    <Precio>31.5</Precio>
    <Tipo1>0</Tipo1>
    <Ditable>0</Ditable>
    <Caducidad>8</Caducidad>
    <Impuesto>0</Impuesto>
    <Multiplo>0</Multiplo>
    <Ingrediente>0</Ingrediente>
  </Table>
  <Table>
    <Tipo>P</Tipo>
    <Codigo>148</Codigo>
    <NoPlu>148</NoPlu>
    <Descripcion>PONDEROSA SALCHICHA C/TOCINO 800 GR PZ</Descripcion>
    <Precio>29.9</Precio>
    <Tipo1>0</Tipo1>
    <Ditable>0</Ditable>
    <Caducidad>8</Caducidad>
    <Impuesto>0</Impuesto>
    <Multiplo>0</Multiplo>
    <Ingrediente>0</Ingrediente>
  </Table>
  <Table>
    <Tipo>P</Tipo>
    <Codigo>149</Codigo>
    <NoPlu>149</NoPlu>
    <Descripcion>PONDEROSA SALCHICHA P/ASAR DE PAVO 800 GR PAQ</Descripcion>
    <Precio>29.5</Precio>
    <Tipo1>0</Tipo1>
    <Ditable>0</Ditable>
    <Caducidad>8</Caducidad>
    <Impuesto>0</Impuesto>
    <Multiplo>0</Multiplo>
    <Ingrediente>0</Ingrediente>
  </Table>
  <Table>
    <Tipo>P</Tipo>
    <Codigo>150</Codigo>
    <NoPlu>150</NoPlu>
    <Descripcion>PONDEROSA SALCHICHA QUESO Y JALAPEÑO 400 GR PZ</Descripcion>
    <Precio>24.9</Precio>
    <Tipo1>0</Tipo1>
    <Ditable>0</Ditable>
    <Caducidad>8</Caducidad>
    <Impuesto>0</Impuesto>
    <Multiplo>0</Multiplo>
    <Ingrediente>0</Ingrediente>
  </Table>
  <Table>
    <ID>2</ID>
    <Tipo>C</Tipo>
    <Codigo>0</Codigo>
    <NoPlu>0</NoPlu>
    <Descripcion>Pavo</Descripcion>
    <Precio>0</Precio>
    <Tipo1>0</Tipo1>
    <Ditable>0</Ditable>
    <Caducidad>0</Caducidad>
    <Impuesto>0</Impuesto>
    <Multiplo>0</Multiplo>
    <Ingrediente>0</Ingrediente>
  </Table>
  <Table>
    <ID>7</ID>
    <Dependencia>2</Dependencia>
    <Tipo>C</Tipo>
    <Codigo>0</Codigo>
    <NoPlu>0</NoPlu>
    <Descripcion>Jamón de pavo</Descripcion>
    <Precio>0</Precio>
    <Tipo1>0</Tipo1>
    <Ditable>0</Ditable>
    <Caducidad>0</Caducidad>
    <Impuesto>0</Impuesto>
    <Multiplo>0</Multiplo>
    <Ingrediente>0</Ingrediente>
  </Table>
  <Table>
    <Tipo>P</Tipo>
    <Codigo>151</Codigo>
    <NoPlu>151</NoPlu>
    <Descripcion>SAN RAFAEL JAMÓN DE PAVO REAL </Descripcion>
    <Precio>93.9</Precio>
    <Tipo1>1</Tipo1>
    <Ditable>1</Ditable>
    <Caducidad>9</Caducidad>
    <Impuesto>0</Impuesto>
    <Multiplo>0</Multiplo>
    <Ingrediente>0</Ingrediente>
  </Table>
  <Table>
    <Tipo>P</Tipo>
    <Codigo>152</Codigo>
    <NoPlu>152</NoPlu>
    <Descripcion>CHIMEX JAMÓN DE PAVO </Descripcion>
    <Precio>45.5</Precio>
    <Tipo1>1</Tipo1>
    <Ditable>1</Ditable>
    <Caducidad>9</Caducidad>
    <Impuesto>0</Impuesto>
    <Multiplo>0</Multiplo>
    <Ingrediente>0</Ingrediente>
  </Table>
  <Table>
    <Tipo>P</Tipo>
    <Codigo>153</Codigo>
    <NoPlu>153</NoPlu>
    <Descripcion>SAN RAFAEL JAMÓN DE PAVO AHUMADO AHUMADO AHUMADO </Descripcion>
    <Precio>109.5</Precio>
    <Tipo1>1</Tipo1>
    <Ditable>1</Ditable>
    <Caducidad>9</Caducidad>
    <Impuesto>0</Impuesto>
    <Multiplo>0</Multiplo>
    <Ingrediente>0</Ingrediente>
  </Table>
  <Table>
    <Tipo>P</Tipo>
    <Codigo>154</Codigo>
    <NoPlu>154</NoPlu>
    <Descripcion>FUD JAMÓN DE PAVO AHUMADO </Descripcion>
    <Precio>86.9</Precio>
    <Tipo1>1</Tipo1>
    <Ditable>1</Ditable>
    <Caducidad>9</Caducidad>
    <Impuesto>0</Impuesto>
    <Multiplo>0</Multiplo>
    <Ingrediente>0</Ingrediente>
  </Table>
  <Table>
    <Tipo>P</Tipo>
    <Codigo>155</Codigo>
    <NoPlu>155</NoPlu>
    <Descripcion>KIR JAMÓN DE PAVO AHUMADO AHUMADO AHUMADO .</Descripcion>
    <Precio>72.9</Precio>
    <Tipo1>1</Tipo1>
    <Ditable>1</Ditable>
    <Caducidad>9</Caducidad>
    <Impuesto>0</Impuesto>
    <Multiplo>0</Multiplo>
    <Ingrediente>0</Ingrediente>
  </Table>
  <Table>
    <Tipo>P</Tipo>
    <Codigo>156</Codigo>
    <NoPlu>156</NoPlu>
    <Descripcion>BAFAR JAMÓN DE PAVO </Descripcion>
    <Precio>42.5</Precio>
    <Tipo1>1</Tipo1>
    <Ditable>1</Ditable>
    <Caducidad>9</Caducidad>
    <Impuesto>0</Impuesto>
    <Multiplo>0</Multiplo>
    <Ingrediente>0</Ingrediente>
  </Table>
  <Table>
    <Tipo>P</Tipo>
    <Codigo>157</Codigo>
    <NoPlu>157</NoPlu>
    <Descripcion>PREMIUM TURK JAMÓN DE PAVO AHUMADO AHUMADO AHUMADO </Descripcion>
    <Precio>97.9</Precio>
    <Tipo1>1</Tipo1>
    <Ditable>1</Ditable>
    <Caducidad>9</Caducidad>
    <Impuesto>0</Impuesto>
    <Multiplo>0</Multiplo>
    <Ingrediente>0</Ingrediente>
  </Table>
  <Table>
    <Tipo>P</Tipo>
    <Codigo>158</Codigo>
    <NoPlu>158</NoPlu>
    <Descripcion>PONDEROSA JAMÓN PAVO </Descripcion>
    <Precio>39.9</Precio>
    <Tipo1>1</Tipo1>
    <Ditable>1</Ditable>
    <Caducidad>9</Caducidad>
    <Impuesto>0</Impuesto>
    <Multiplo>0</Multiplo>
    <Ingrediente>0</Ingrediente>
  </Table>
  <Table>
    <Tipo>P</Tipo>
    <Codigo>159</Codigo>
    <NoPlu>159</NoPlu>
    <Descripcion>TANGAMANGA JAMÓN DE PAVO </Descripcion>
    <Precio>110.5</Precio>
    <Tipo1>1</Tipo1>
    <Ditable>1</Ditable>
    <Caducidad>9</Caducidad>
    <Impuesto>0</Impuesto>
    <Multiplo>0</Multiplo>
    <Ingrediente>0</Ingrediente>
  </Table>
  <Table>
    <Tipo>P</Tipo>
    <Codigo>160</Codigo>
    <NoPlu>160</NoPlu>
    <Descripcion>BAFAR JAMÓN AHUMADO DE PAVO </Descripcion>
    <Precio>69.9</Precio>
    <Tipo1>1</Tipo1>
    <Ditable>1</Ditable>
    <Caducidad>9</Caducidad>
    <Impuesto>0</Impuesto>
    <Multiplo>0</Multiplo>
    <Ingrediente>0</Ingrediente>
  </Table>
  <Table>
    <Tipo>P</Tipo>
    <Codigo>161</Codigo>
    <NoPlu>161</NoPlu>
    <Descripcion>SUPREMO JAMÓN DE PAVO </Descripcion>
    <Precio>46.9</Precio>
    <Tipo1>1</Tipo1>
    <Ditable>1</Ditable>
    <Caducidad>9</Caducidad>
    <Impuesto>0</Impuesto>
    <Multiplo>0</Multiplo>
    <Ingrediente>0</Ingrediente>
  </Table>
  <Table>
    <Tipo>P</Tipo>
    <Codigo>162</Codigo>
    <NoPlu>162</NoPlu>
    <Descripcion>SABORI JAMÓN PAVO NATURAL </Descripcion>
    <Precio>92.9</Precio>
    <Tipo1>1</Tipo1>
    <Ditable>1</Ditable>
    <Caducidad>9</Caducidad>
    <Impuesto>0</Impuesto>
    <Multiplo>0</Multiplo>
    <Ingrediente>0</Ingrediente>
  </Table>
  <Table>
    <Tipo>P</Tipo>
    <Codigo>163</Codigo>
    <NoPlu>163</NoPlu>
    <Descripcion>CAROLINA TURKEY JAMÓN PICNIC D PAVO </Descripcion>
    <Precio>28.5</Precio>
    <Tipo1>1</Tipo1>
    <Ditable>1</Ditable>
    <Caducidad>9</Caducidad>
    <Impuesto>0</Impuesto>
    <Multiplo>0</Multiplo>
    <Ingrediente>0</Ingrediente>
  </Table>
  <Table>
    <Tipo>P</Tipo>
    <Codigo>164</Codigo>
    <NoPlu>164</NoPlu>
    <Descripcion>SABORI JAMÓN PAVC/BIFIDUS </Descripcion>
    <Precio>104.9</Precio>
    <Tipo1>1</Tipo1>
    <Ditable>1</Ditable>
    <Caducidad>9</Caducidad>
    <Impuesto>0</Impuesto>
    <Multiplo>0</Multiplo>
    <Ingrediente>0</Ingrediente>
  </Table>
  <Table>
    <Tipo>P</Tipo>
    <Codigo>165</Codigo>
    <NoPlu>165</NoPlu>
    <Descripcion>ZWAN JAMÓN PAVO NATURAL </Descripcion>
    <Precio>95.9</Precio>
    <Tipo1>1</Tipo1>
    <Ditable>1</Ditable>
    <Caducidad>9</Caducidad>
    <Impuesto>0</Impuesto>
    <Multiplo>0</Multiplo>
    <Ingrediente>0</Ingrediente>
  </Table>
  <Table>
    <ID>8</ID>
    <Dependencia>2</Dependencia>
    <Tipo>C</Tipo>
    <Codigo>0</Codigo>
    <NoPlu>0</NoPlu>
    <Descripcion>Salchicha de pavo</Descripcion>
    <Precio>0</Precio>
    <Tipo1>0</Tipo1>
    <Ditable>0</Ditable>
    <Caducidad>0</Caducidad>
    <Impuesto>0</Impuesto>
    <Multiplo>0</Multiplo>
    <Ingrediente>0</Ingrediente>
  </Table>
  <Table>
    <Tipo>P</Tipo>
    <Codigo>166</Codigo>
    <NoPlu>166</NoPlu>
    <Descripcion>SAN RAFAEL SALCHICHA DE PAVO </Descripcion>
    <Precio>44.5</Precio>
    <Tipo1>1</Tipo1>
    <Ditable>1</Ditable>
    <Caducidad>10</Caducidad>
    <Impuesto>0</Impuesto>
    <Multiplo>0</Multiplo>
    <Ingrediente>0</Ingrediente>
  </Table>
  <Table>
    <Tipo>P</Tipo>
    <Codigo>167</Codigo>
    <NoPlu>167</NoPlu>
    <Descripcion>FUD SALCHICHA DE PAVO </Descripcion>
    <Precio>36.5</Precio>
    <Tipo1>1</Tipo1>
    <Ditable>1</Ditable>
    <Caducidad>10</Caducidad>
    <Impuesto>0</Impuesto>
    <Multiplo>0</Multiplo>
    <Ingrediente>0</Ingrediente>
  </Table>
  <Table>
    <Tipo>P</Tipo>
    <Codigo>168</Codigo>
    <NoPlu>168</NoPlu>
    <Descripcion>KIR SALCHICHA DE PAVO DE PAVO DE PAVO </Descripcion>
    <Precio>32.9</Precio>
    <Tipo1>1</Tipo1>
    <Ditable>1</Ditable>
    <Caducidad>10</Caducidad>
    <Impuesto>0</Impuesto>
    <Multiplo>0</Multiplo>
    <Ingrediente>0</Ingrediente>
  </Table>
  <Table>
    <Tipo>P</Tipo>
    <Codigo>169</Codigo>
    <NoPlu>169</NoPlu>
    <Descripcion>CHIMEX SALCHICHA DE PAVO </Descripcion>
    <Precio>31.5</Precio>
    <Tipo1>1</Tipo1>
    <Ditable>1</Ditable>
    <Caducidad>10</Caducidad>
    <Impuesto>0</Impuesto>
    <Multiplo>0</Multiplo>
    <Ingrediente>0</Ingrediente>
  </Table>
  <Table>
    <Tipo>P</Tipo>
    <Codigo>170</Codigo>
    <NoPlu>170</NoPlu>
    <Descripcion>FUD SALCHICHA JUMBO DE PAVO </Descripcion>
    <Precio>37.9</Precio>
    <Tipo1>1</Tipo1>
    <Ditable>1</Ditable>
    <Caducidad>10</Caducidad>
    <Impuesto>0</Impuesto>
    <Multiplo>0</Multiplo>
    <Ingrediente>0</Ingrediente>
  </Table>
  <Table>
    <Tipo>P</Tipo>
    <Codigo>171</Codigo>
    <NoPlu>171</NoPlu>
    <Descripcion>PREMIUM TURK SALCHICHA DE PAVO </Descripcion>
    <Precio>37.5</Precio>
    <Tipo1>1</Tipo1>
    <Ditable>1</Ditable>
    <Caducidad>10</Caducidad>
    <Impuesto>0</Impuesto>
    <Multiplo>0</Multiplo>
    <Ingrediente>0</Ingrediente>
  </Table>
  <Table>
    <Tipo>P</Tipo>
    <Codigo>172</Codigo>
    <NoPlu>172</NoPlu>
    <Descripcion>PONDEROSA SALCHICHA PAVO </Descripcion>
    <Precio>27.5</Precio>
    <Tipo1>1</Tipo1>
    <Ditable>1</Ditable>
    <Caducidad>10</Caducidad>
    <Impuesto>0</Impuesto>
    <Multiplo>0</Multiplo>
    <Ingrediente>0</Ingrediente>
  </Table>
  <Table>
    <Tipo>P</Tipo>
    <Codigo>173</Codigo>
    <NoPlu>173</NoPlu>
    <Descripcion>SUPREMO SALCHICHA DE PAVO </Descripcion>
    <Precio>32.9</Precio>
    <Tipo1>1</Tipo1>
    <Ditable>1</Ditable>
    <Caducidad>10</Caducidad>
    <Impuesto>0</Impuesto>
    <Multiplo>0</Multiplo>
    <Ingrediente>0</Ingrediente>
  </Table>
  <Table>
    <Tipo>P</Tipo>
    <Codigo>174</Codigo>
    <NoPlu>174</NoPlu>
    <Descripcion>BAFAR SALCHICHA FRANKFURT PAVO </Descripcion>
    <Precio>27.9</Precio>
    <Tipo1>1</Tipo1>
    <Ditable>1</Ditable>
    <Caducidad>10</Caducidad>
    <Impuesto>0</Impuesto>
    <Multiplo>0</Multiplo>
    <Ingrediente>0</Ingrediente>
  </Table>
  <Table>
    <Tipo>P</Tipo>
    <Codigo>175</Codigo>
    <NoPlu>175</NoPlu>
    <Descripcion>DUBY SALCHICHA DE PAVO </Descripcion>
    <Precio>27.5</Precio>
    <Tipo1>1</Tipo1>
    <Ditable>1</Ditable>
    <Caducidad>10</Caducidad>
    <Impuesto>0</Impuesto>
    <Multiplo>0</Multiplo>
    <Ingrediente>0</Ingrediente>
  </Table>
  <Table>
    <Tipo>P</Tipo>
    <Codigo>176</Codigo>
    <NoPlu>176</NoPlu>
    <Descripcion>SABORI SALCHICHA DE PAVO </Descripcion>
    <Precio>42.9</Precio>
    <Tipo1>1</Tipo1>
    <Ditable>1</Ditable>
    <Caducidad>10</Caducidad>
    <Impuesto>0</Impuesto>
    <Multiplo>0</Multiplo>
    <Ingrediente>0</Ingrediente>
  </Table>
  <Table>
    <Tipo>P</Tipo>
    <Codigo>177</Codigo>
    <NoPlu>177</NoPlu>
    <Descripcion>CARNELI SALCHICHA PAVO </Descripcion>
    <Precio>36.9</Precio>
    <Tipo1>1</Tipo1>
    <Ditable>1</Ditable>
    <Caducidad>10</Caducidad>
    <Impuesto>0</Impuesto>
    <Multiplo>0</Multiplo>
    <Ingrediente>0</Ingrediente>
  </Table>
  <Table>
    <ID>9</ID>
    <Dependencia>2</Dependencia>
    <Tipo>C</Tipo>
    <Codigo>0</Codigo>
    <NoPlu>0</NoPlu>
    <Descripcion>Pechuga de pavo</Descripcion>
    <Precio>0</Precio>
    <Tipo1>0</Tipo1>
    <Ditable>0</Ditable>
    <Caducidad>0</Caducidad>
    <Impuesto>0</Impuesto>
    <Multiplo>0</Multiplo>
    <Ingrediente>0</Ingrediente>
  </Table>
  <Table>
    <Tipo>P</Tipo>
    <Codigo>178</Codigo>
    <NoPlu>178</NoPlu>
    <Descripcion>SAN RAFAEL PECHUGA DE PAVO </Descripcion>
    <Precio>93.5</Precio>
    <Tipo1>1</Tipo1>
    <Ditable>1</Ditable>
    <Caducidad>5</Caducidad>
    <Impuesto>0</Impuesto>
    <Multiplo>0</Multiplo>
    <Ingrediente>0</Ingrediente>
  </Table>
  <Table>
    <Tipo>P</Tipo>
    <Codigo>179</Codigo>
    <NoPlu>179</NoPlu>
    <Descripcion>FUD PECHUGA DE PAVO </Descripcion>
    <Precio>99.9</Precio>
    <Tipo1>1</Tipo1>
    <Ditable>1</Ditable>
    <Caducidad>5</Caducidad>
    <Impuesto>0</Impuesto>
    <Multiplo>0</Multiplo>
    <Ingrediente>0</Ingrediente>
  </Table>
  <Table>
    <Tipo>P</Tipo>
    <Codigo>180</Codigo>
    <NoPlu>180</NoPlu>
    <Descripcion>SABORI PECHUGA DE PAVO EXTRAFINA SABORI </Descripcion>
    <Precio>110.9</Precio>
    <Tipo1>1</Tipo1>
    <Ditable>1</Ditable>
    <Caducidad>5</Caducidad>
    <Impuesto>0</Impuesto>
    <Multiplo>0</Multiplo>
    <Ingrediente>0</Ingrediente>
  </Table>
  <Table>
    <Tipo>P</Tipo>
    <Codigo>181</Codigo>
    <NoPlu>181</NoPlu>
    <Descripcion>BAFAR PECHUGA DE PAVO </Descripcion>
    <Precio>79.9</Precio>
    <Tipo1>1</Tipo1>
    <Ditable>1</Ditable>
    <Caducidad>5</Caducidad>
    <Impuesto>0</Impuesto>
    <Multiplo>0</Multiplo>
    <Ingrediente>0</Ingrediente>
  </Table>
  <Table>
    <Tipo>P</Tipo>
    <Codigo>182</Codigo>
    <NoPlu>182</NoPlu>
    <Descripcion>CARNELI PECHUGA PAVO </Descripcion>
    <Precio>91.5</Precio>
    <Tipo1>1</Tipo1>
    <Ditable>1</Ditable>
    <Caducidad>5</Caducidad>
    <Impuesto>0</Impuesto>
    <Multiplo>0</Multiplo>
    <Ingrediente>0</Ingrediente>
  </Table>
  <Table>
    <Tipo>P</Tipo>
    <Codigo>183</Codigo>
    <NoPlu>183</NoPlu>
    <Descripcion>CAROLINA TURKEY PECHUGA DE PAVO AHUMADA PETITE </Descripcion>
    <Precio>84.9</Precio>
    <Tipo1>1</Tipo1>
    <Ditable>1</Ditable>
    <Caducidad>5</Caducidad>
    <Impuesto>0</Impuesto>
    <Multiplo>0</Multiplo>
    <Ingrediente>0</Ingrediente>
  </Table>
  <Table>
    <Tipo>P</Tipo>
    <Codigo>184</Codigo>
    <NoPlu>184</NoPlu>
    <Descripcion>CAROLINA TURKEY PECHUGA PREMIUM </Descripcion>
    <Precio>95.9</Precio>
    <Tipo1>1</Tipo1>
    <Ditable>1</Ditable>
    <Caducidad>5</Caducidad>
    <Impuesto>0</Impuesto>
    <Multiplo>0</Multiplo>
    <Ingrediente>0</Ingrediente>
  </Table>
  <Table>
    <Tipo>P</Tipo>
    <Codigo>185</Codigo>
    <NoPlu>185</NoPlu>
    <Descripcion>CAROLINA TURKEY PECHUGA TRADICIONAL </Descripcion>
    <Precio>97.5</Precio>
    <Tipo1>1</Tipo1>
    <Ditable>1</Ditable>
    <Caducidad>5</Caducidad>
    <Impuesto>0</Impuesto>
    <Multiplo>0</Multiplo>
    <Ingrediente>0</Ingrediente>
  </Table>
  <Table>
    <Tipo>P</Tipo>
    <Codigo>186</Codigo>
    <NoPlu>186</NoPlu>
    <Descripcion>SAN RAFAEL PECHUGA NATURAL </Descripcion>
    <Precio>106.5</Precio>
    <Tipo1>1</Tipo1>
    <Ditable>1</Ditable>
    <Caducidad>5</Caducidad>
    <Impuesto>0</Impuesto>
    <Multiplo>0</Multiplo>
    <Ingrediente>0</Ingrediente>
  </Table>
  <Table>
    <Tipo>P</Tipo>
    <Codigo>187</Codigo>
    <NoPlu>187</NoPlu>
    <Descripcion>SAN RAFAEL PECHUGA PAVO HORNEADO </Descripcion>
    <Precio>106.5</Precio>
    <Tipo1>1</Tipo1>
    <Ditable>1</Ditable>
    <Caducidad>5</Caducidad>
    <Impuesto>0</Impuesto>
    <Multiplo>0</Multiplo>
    <Ingrediente>0</Ingrediente>
  </Table>
  <Table>
    <Tipo>P</Tipo>
    <Codigo>188</Codigo>
    <NoPlu>188</NoPlu>
    <Descripcion>ZWAN PECHUGA DE PAVO </Descripcion>
    <Precio>99.9</Precio>
    <Tipo1>1</Tipo1>
    <Ditable>1</Ditable>
    <Caducidad>5</Caducidad>
    <Impuesto>0</Impuesto>
    <Multiplo>0</Multiplo>
    <Ingrediente>0</Ingrediente>
  </Table>
  <Table>
    <Tipo>P</Tipo>
    <Codigo>189</Codigo>
    <NoPlu>189</NoPlu>
    <Descripcion>ZWAN PECHUGA DE PAVO HORNEADA </Descripcion>
    <Precio>109.9</Precio>
    <Tipo1>1</Tipo1>
    <Ditable>1</Ditable>
    <Caducidad>5</Caducidad>
    <Impuesto>0</Impuesto>
    <Multiplo>0</Multiplo>
    <Ingrediente>0</Ingrediente>
  </Table>
  <Table>
    <ID>10</ID>
    <Dependencia>2</Dependencia>
    <Tipo>C</Tipo>
    <Codigo>0</Codigo>
    <NoPlu>0</NoPlu>
    <Descripcion>Pavo crudo</Descripcion>
    <Precio>0</Precio>
    <Tipo1>0</Tipo1>
    <Ditable>0</Ditable>
    <Caducidad>0</Caducidad>
    <Impuesto>0</Impuesto>
    <Multiplo>0</Multiplo>
    <Ingrediente>0</Ingrediente>
  </Table>
  <Table>
    <Tipo>P</Tipo>
    <Codigo>190</Codigo>
    <NoPlu>190</NoPlu>
    <Descripcion>MEZORO CARNE MOLIDA DE PAVO 500 GRAMO(S) PZ</Descripcion>
    <Precio>21.9</Precio>
    <Tipo1>0</Tipo1>
    <Ditable>0</Ditable>
    <Caducidad>6</Caducidad>
    <Impuesto>0</Impuesto>
    <Multiplo>0</Multiplo>
    <Ingrediente>0</Ingrediente>
  </Table>
  <Table>
    <ID>11</ID>
    <Dependencia>2</Dependencia>
    <Tipo>C</Tipo>
    <Codigo>0</Codigo>
    <NoPlu>0</NoPlu>
    <Descripcion>Pavo ahumado</Descripcion>
    <Precio>0</Precio>
    <Tipo1>0</Tipo1>
    <Ditable>0</Ditable>
    <Caducidad>0</Caducidad>
    <Impuesto>0</Impuesto>
    <Multiplo>0</Multiplo>
    <Ingrediente>0</Ingrediente>
  </Table>
  <Table>
    <Tipo>P</Tipo>
    <Codigo>191</Codigo>
    <NoPlu>191</NoPlu>
    <Descripcion>SAN RAFAEL JAMÓN DE PAVO AHUMADO AHUMADO AHUMADO </Descripcion>
    <Precio>109.5</Precio>
    <Tipo1>1</Tipo1>
    <Ditable>0</Ditable>
    <Caducidad>7</Caducidad>
    <Impuesto>0</Impuesto>
    <Multiplo>0</Multiplo>
    <Ingrediente>0</Ingrediente>
  </Table>
  <Table>
    <Tipo>P</Tipo>
    <Codigo>192</Codigo>
    <NoPlu>192</NoPlu>
    <Descripcion>FUD JAMÓN DE PAVO AHUMADO </Descripcion>
    <Precio>86.9</Precio>
    <Tipo1>1</Tipo1>
    <Ditable>0</Ditable>
    <Caducidad>7</Caducidad>
    <Impuesto>0</Impuesto>
    <Multiplo>0</Multiplo>
    <Ingrediente>0</Ingrediente>
  </Table>
  <Table>
    <Tipo>P</Tipo>
    <Codigo>193</Codigo>
    <NoPlu>193</NoPlu>
    <Descripcion>KIR JAMÓN DE PAVO AHUMADO AHUMADO AHUMADO .</Descripcion>
    <Precio>72.9</Precio>
    <Tipo1>1</Tipo1>
    <Ditable>0</Ditable>
    <Caducidad>7</Caducidad>
    <Impuesto>0</Impuesto>
    <Multiplo>0</Multiplo>
    <Ingrediente>0</Ingrediente>
  </Table>
  <Table>
    <Tipo>P</Tipo>
    <Codigo>194</Codigo>
    <NoPlu>194</NoPlu>
    <Descripcion>PREMIUM TURK JAMÓN DE PAVO AHUMADO AHUMADO AHUMADO </Descripcion>
    <Precio>97.9</Precio>
    <Tipo1>1</Tipo1>
    <Ditable>0</Ditable>
    <Caducidad>7</Caducidad>
    <Impuesto>0</Impuesto>
    <Multiplo>0</Multiplo>
    <Ingrediente>0</Ingrediente>
  </Table>
  <Table>
    <Tipo>P</Tipo>
    <Codigo>195</Codigo>
    <NoPlu>195</NoPlu>
    <Descripcion>BAFAR JAMÓN AHUMADO DE PAVO </Descripcion>
    <Precio>69.9</Precio>
    <Tipo1>1</Tipo1>
    <Ditable>0</Ditable>
    <Caducidad>7</Caducidad>
    <Impuesto>0</Impuesto>
    <Multiplo>0</Multiplo>
    <Ingrediente>0</Ingrediente>
  </Table>
</NewDataSet>